{"name": "Війна", "id": 1020620, "predecessors": [{"name": "Військова_справа", "id": 16457}, {"name": "Надзвичайні_ситуації", "id": 1313023}, {"name": "Насильство", "id": 1624692}, {"name": "Міжособові_стосунки", "id": 726630}], "successors": [{"name": "Портал:Війна", "id": 1926999}, {"name": "Війни_США", "id": 161597}, {"name": "Війни_Іспанії", "id": 177249}, {"name": "Війни_Франції", "id": 240709}, {"name": "Війни_Японії", "id": 361131}, {"name": "Війни_Китаю", "id": 361133}, {"name": "Війни_Швеції", "id": 374998}, {"name": "Війни_Великої_Британії", "id": 405264}, {"name": "Війни_Індії", "id": 811275}, {"name": "Війни_Португалії", "id": 811280}, {"name": "Війни_Польщі", "id": 1484784}, {"name": "Війни_Османської_імперії", "id": 1605339}, {"name": "Жінки-військовики", "id": 2604964}, {"name": "Революціонерки", "id": 4319949}, {"name": "Учасниці_воєн", "id": 4517316}, {"name": "Воєнні_злочини", "id": 1500506}, {"name": "Військовополонені", "id": 1734891}, {"name": "Науково-фантастичні_військові_фільми", "id": 2673395}, {"name": "Воєнні_фільми_України", "id": 1748851}, {"name": "Воєнні_фільми_США", "id": 1748867}, {"name": "Воєнні_фільми_Франції", "id": 1753276}, {"name": "Воєнні_фільми_Великої_Британії", "id": 1764836}, {"name": "Воєнні_фільми_СРСР", "id": 1788156}, {"name": "Воєнні_фільми_Росії", "id": 1791745}, {"name": "Наслідки_Другої_світової_війни", "id": 1237104}, {"name": "Військові_втрати", "id": 1558914}, {"name": "Північна_війна_(1700—1721)", "id": 154924}, {"name": "Воєнні_епічні_фільми", "id": 2271506}, {"name": "Антивоєнні_фільми", "id": 2297462}, {"name": "Фільми_про_ядерну_війну_та_зброю", "id": 4336190}, {"name": "Українсько-польська_війна_в_Галичині_1918—19", "id": 568541}, {"name": "Війна_в_Афганістані_(2001–2021)", "id": 1725006}, {"name": "Війна_на_сході_України", "id": 1866147}, {"name": "Битви_України", "id": 2258886}, {"name": "Битви_в_Україні", "id": 37348}, {"name": "Громадянська_війна_в_Росії", "id": 286496}, {"name": "Кримська_війна", "id": 403536}, {"name": "Ватажки_повстань", "id": 232553}, {"name": "Війни_Стародавнього_Риму", "id": 1456793}, {"name": "Наполеонівські_війни", "id": 83386}, {"name": "Учасники_австро-прусської_війни", "id": 4114836}, {"name": "Учасники_радянсько-фінської_війни", "id": 412747}, {"name": "Учасники_Польського_походу_РСЧА", "id": 568366}, {"name": "Учасники_радянсько-японської_війни", "id": 598942}, {"name": "Учасники_Корейської_війни", "id": 656283}, {"name": "Учасники_Афганської_війни_(1979—1989)", "id": 744704}, {"name": "Учасники_Другої_чеченської_війни", "id": 818930}, {"name": "Учасники_Першої_чеченської_війни", "id": 818931}, {"name": "Учасники_російсько-японської_війни", "id": 973016}, {"name": "Учасники_В'єтнамської_війни", "id": 1061959}, {"name": "Учасники_Тридцятирічної_війни", "id": 1304067}, {"name": "Учасники_війни_в_Афганістані_(з_2001_року)", "id": 1567478}, {"name": "Учасники_війни_в_Іраку", "id": 1567479}, {"name": "Учасники_французько-прусської_війни", "id": 1736781}, {"name": "Учасники_Семирічної_війни", "id": 1977821}, {"name": "Учасники_війни_в_Перській_затоці", "id": 2120037}, {"name": "Учасники_наполеонівських_війн", "id": 2181693}, {"name": "Учасники_Кавказьких_війн", "id": 2181710}, {"name": "Учасники_російсько-грузинської_війни_(2008)", "id": 2448290}, {"name": "Учасники_Першої_Балканської_війни", "id": 2552136}, {"name": "Учасники_війни_за_австрійську_спадщину", "id": 2603365}, {"name": "Учасники_Лівонської_війни", "id": 3720304}, {"name": "Учасники_Галльської_війни", "id": 5366951}, {"name": "Військові_формування_України_у_російсько-українській_війні_(з_2014)", "id": 2250246}, {"name": "Військові_формування_Росії_у_російсько-українській_війні_(з_2014)", "id": 4495422}, {"name": "Терористичні_збройні_формування_«ДНР»_і_«ЛНР»", "id": 1967813}, {"name": "Кадрові_формування_ЗС_РФ_у_російсько-українській_війні_(з_2014)", "id": 2209765}, {"name": "Українські_воїни,_загиблі_у_російсько-українській_війні_(з_2014)", "id": 2345133}, {"name": "Втрати_в_російсько-українській_війні_за_формуванням_(Україна)", "id": 2345031}, {"name": "Втрати_в_російсько-українській_війні_за_місцем_бою", "id": 2345033}, {"name": "Втрати_в_російсько-українській_війні_за_формуванням_(РФ)", "id": 4705682}, {"name": "Втрати_в_російсько-українській_війні_за_хронологією", "id": 5106457}, {"name": "Країни-учасники_Другої_світової_війни", "id": 820460}, {"name": "Естонія_в_Другій_світовій_війні", "id": 1024314}, {"name": "Арабо-ізраїльський_конфлікт", "id": 446400}, {"name": "Воєнні_злочинці", "id": 741849}, {"name": "Загинули_в_бою", "id": 773087}, {"name": "Партизани", "id": 1716203}, {"name": "Військові_кореспонденти", "id": 2146258}, {"name": "Учасники_Польського_повстання_(1863—1864)", "id": 641150}, {"name": "Учасники_Листопадового_повстання_(1830—1831)", "id": 1243592}, {"name": "Учасники_Варшавського_повстання_1944_року", "id": 2025287}, {"name": "Учасники_Каппського_заколоту", "id": 5226887}, {"name": "Учасники_придушення_Угорського_повстання_1956", "id": 1537785}, {"name": "Російсько-українські_битви", "id": 454794}, {"name": "Тарговицькі_конфедерати", "id": 3861405}, {"name": "Російсько-українська_війна_(з_2014)", "id": 1680316}, {"name": "Радянсько-українська_війна", "id": 1939933}, {"name": "Учасники_російсько-української_війни_(з_2014)", "id": 1731635}, {"name": "Учасники_радянсько-української_війни_1917-1921", "id": 1939929}, {"name": "Партизанські_рухи", "id": 875247}, {"name": "Партизанські_війни", "id": 4751300}]}