{"name": "Папство", "id": 1102275, "predecessors": [{"name": "Католицизм", "id": 15030}, {"name": "Історична_географія", "id": 30433}, {"name": "Політична_географія", "id": 18954}, {"name": "Головна", "id": 13205}], "successors": [{"name": "Папи", "id": 23760}, {"name": "Папські_енцикліки", "id": 898189}, {"name": "Римська_курія", "id": 902432}, {"name": "Члени_Папської_академії_наук", "id": 985845}, {"name": "Випускники_Папської_церковної_академії", "id": 2437451}, {"name": "Випускники_Папської_Грецької_колегії_святого_Атанасія", "id": 2246758}, {"name": "Дворянство_Святого_Престолу", "id": 2959549}, {"name": "Беатифіковані_папою_Іваном_Павлом_II", "id": 4384655}]}