{"name": "Дружини_керівників_держав", "id": 1381376, "predecessors": [{"name": "Глави_держав", "id": 2201551}, {"name": "Жінки-політики", "id": 1057309}, {"name": "Шлюб", "id": 539112}], "successors": [{"name": "Королеви_та_імператриці_Франції", "id": 3418314}, {"name": "Консортки", "id": 4367106}, {"name": "Дружини_монархів_Швеції", "id": 1501787}, {"name": "Княгині_і_королеви_Польщі", "id": 2115996}, {"name": "Дружини_османських_султанів", "id": 2117551}, {"name": "Угорські_королеви", "id": 2587948}, {"name": "Руські_княгині", "id": 2565468}, {"name": "Руські_князівни", "id": 2567355}, {"name": "Перші_леді_США", "id": 1471384}]}