{"name": "Почесні_доктори", "id": 1572985, "predecessors": [{"name": "Соціальна_структура_та_стратифікація", "id": 253571}, {"name": "Наукові_ступені_й_учені_звання", "id": 249527}], "successors": [{"name": "Почесні_доктори_Єльського_університету", "id": 2172137}, {"name": "Почесні_доктори_Гарвардського_університету", "id": 2176850}, {"name": "Почесні_доктори_Університету_Маямі", "id": 4538515}, {"name": "Почесні_доктори_Афінського_університету", "id": 2176327}, {"name": "Почесні_доктори_Оксфордського_університету", "id": 1572980}, {"name": "Почесні_доктори_Університету_Сент-Ендрюса", "id": 4736163}, {"name": "Почесні_доктори_Університету_Осло", "id": 2177566}, {"name": "Почесні_доктори_Женевського_університету", "id": 2206464}, {"name": "Почесні_доктори_Уппсальського_університету", "id": 3136350}, {"name": "Почесні_доктори_Мадридського_університету_Комплутенсе", "id": 4515865}, {"name": "Почесні_доктори_Ягеллонського_університету", "id": 2145780}, {"name": "Почесні_доктори_Університету_Лаваля", "id": 4734517}]}