{"name": "Шаблони:Політика", "id": 165569, "predecessors": [{"name": "Шаблони", "id": 41618}], "successors": [{"name": "Навігаційні_шаблони:Політика", "id": 1002296}, {"name": "Шаблони:Політичні_переконання", "id": 5125410}, {"name": "Навігаційні_шаблони:Вибори", "id": 1783040}, {"name": "Навігаційні_шаблони:Політика_України", "id": 2612580}, {"name": "Шаблони:Кольори_політичних_партій", "id": 2450309}, {"name": "Шаблони:Короткі_назви_політичних_партій", "id": 3112442}, {"name": "Шаблони_кольорів_політичних_партій_України", "id": 772427}, {"name": "Шаблони_коротких_назв_політичних_партій_України", "id": 3112487}]}