{"name": "Учасники_російсько-української_війни_(з_2014)", "id": 1731635, "predecessors": [{"name": "Війни_XXI_століття", "id": 1628713}, {"name": "Війна", "id": 1020620}, {"name": "Головна", "id": 13205}], "successors": [{"name": "Українські_воїни-учасники_російсько-української_війни_(з_2014)", "id": 1747636}, {"name": "Волонтери_АТО", "id": 1830164}, {"name": "Проросійські_бойовики_російсько-української_війни_(2014-донині)", "id": 1891447}, {"name": "Списки_учасників_російсько-української_війни", "id": 2024463}, {"name": "Російські_військові_у_війні_проти_України_(з_2014)", "id": 2564003}, {"name": "Кіборги_Донецького_аеропорту", "id": 4784384}, {"name": "Учасники_боїв_за_Київ", "id": 4467204}, {"name": "Учасники_битви_за_Маріуполь_(2022)", "id": 4790711}, {"name": "Учасники_боїв_за_Харків", "id": 4790749}, {"name": "Учасники_боїв_за_Херсон", "id": 4791722}, {"name": "Учасники_боїв_за_Сєвєродонецьк_(2022)", "id": 4791738}, {"name": "Учасники_боїв_за_Бахмут", "id": 4791760}, {"name": "Учасники_боїв_за_Ізюм", "id": 4793031}, {"name": "Учасники_боїв_за_Миколаїв", "id": 4793942}, {"name": "Учасники_боїв_за_Авдіївку", "id": 4795053}, {"name": "Учасники_боїв_за_Мар'їнку", "id": 4798624}, {"name": "Учасники_боїв_на_Світлодарській_дузі", "id": 4802280}]}