{"name": "Письменниці_США", "id": 1800813, "predecessors": [{"name": "Письменники_США", "id": 421447}, {"name": "Жінки_США", "id": 2465194}, {"name": "Головна", "id": 13205}], "successors": [{"name": "Письменниці-фантасти_США", "id": 2692518}, {"name": "Письменниці_США_XX_століття", "id": 3698923}, {"name": "Американські_поетеси", "id": 3705391}, {"name": "Письменниці_США_XXI_століття", "id": 3714199}, {"name": "Американські_сценаристки", "id": 3755009}, {"name": "Американські_мемуаристки", "id": 3756948}, {"name": "Американські_дитячі_письменниці", "id": 3817555}, {"name": "Американські_романістки", "id": 4170132}, {"name": "Письменниці-феміністки_США", "id": 4667051}]}