{"name": "Розділи_екології", "id": 1960869, "predecessors": [{"name": "Екологія", "id": 13577}], "successors": [{"name": "Гідробіологія", "id": 209123}, {"name": "Екологічна_політика", "id": 219020}, {"name": "Екологія_рослин", "id": 600316}, {"name": "Трофічна_екологія", "id": 757810}, {"name": "Екологія_тварин", "id": 771366}, {"name": "Синекологія", "id": 1277920}, {"name": "Екологічна_економіка", "id": 1601202}, {"name": "Фітоценологія", "id": 1843348}, {"name": "Міжнародне_екологічне_право", "id": 507993}, {"name": "Права_тварин", "id": 1637677}, {"name": "Токсикологія", "id": 104140}, {"name": "Харчова_поведінка", "id": 1799993}, {"name": "Антибіотики", "id": 82704}, {"name": "Рамсарські_угіддя_України", "id": 3516449}]}