{"name": "Види_спорту", "id": 21459, "predecessors": [{"name": "Розваги", "id": 188198}], "successors": [{"name": "Водні_види_спорту", "id": 19074}, {"name": "Автоспорт", "id": 32744}, {"name": "Кінний_спорт", "id": 241506}, {"name": "Екстремальні_види_спорту", "id": 243647}, {"name": "Командні_види_спорту", "id": 396230}, {"name": "Спортивні_ігри", "id": 753678}, {"name": "Скелелазіння", "id": 1421023}, {"name": "Ігри_з_м'ячем", "id": 1578074}, {"name": "Тварини_в_спорті", "id": 2362997}, {"name": "Культуристи", "id": 406146}, {"name": "Реслери", "id": 850323}, {"name": "Зображення:Футболісти", "id": 57513}, {"name": "Лауреати_«Золотого_м'яча»", "id": 1108374}, {"name": "Футболісти,_дискваліфіковані_за_вживання_допінгу", "id": 3779772}, {"name": "Олімпійські_чемпіони_з_лижних_перегонів", "id": 798917}, {"name": "Члени_Зали_слави_Світової_легкої_атлетики", "id": 1594472}, {"name": "Легкоатлети,_дискваліфіковані_за_порушення_антидопінгових_правил", "id": 3779770}, {"name": "Призери_з_синхронного_плавання_чемпіонатів_світу_з_водних_видів_спорту", "id": 4578733}, {"name": "Футбольні_воротарі", "id": 309182}, {"name": "Українські_дзюдоїсти", "id": 311128}, {"name": "Японські_дзюдоїсти", "id": 701303}, {"name": "Бойові_мистецтва", "id": 32743}, {"name": "Велоспорт", "id": 32745}, {"name": "Бокс", "id": 32746}, {"name": "Шахові_терміни", "id": 199658}, {"name": "Варіанти_шахів", "id": 354231}, {"name": "Тренери_з_легкої_атлетики", "id": 1346934}, {"name": "Незавершені_статті_з_легкої_атлетики", "id": 2666007}, {"name": "Чемпіони_літніх_Паралімпійських_ігор_з_легкої_атлетики", "id": 5383958}, {"name": "Гімнастика_на_Олімпійських_іграх", "id": 1340809}, {"name": "Чемпіони_світу_з_біатлону", "id": 688079}, {"name": "Олімпійські_чемпіони_зі_спортивної_гімнастики", "id": 801389}, {"name": "Гімнасти_на_літніх_Олімпійських_іграх_2020", "id": 4296861}, {"name": "Спортивні_гімнастки_на_літніх_Олімпійських_іграх_2008", "id": 2512154}, {"name": "Спортивні_гімнасти_на_літніх_Олімпійських_іграх_2008", "id": 2512167}, {"name": "Фехтувальниці", "id": 4345205}, {"name": "Вигадані_фехтувальники", "id": 4427601}, {"name": "Закриті_дебюти", "id": 778563}, {"name": "Відкриті_дебюти", "id": 843231}, {"name": "Члени_Зали_слави_FILA", "id": 2035202}, {"name": "Борці,_дискваліфіковані_за_вживання_допінгу", "id": 3779776}, {"name": "Американські_бійці_змішаного_стилю", "id": 540182}, {"name": "Шахові_композитори", "id": 310249}, {"name": "Олімпійські_чемпіони_зі_сноубордингу", "id": 800405}, {"name": "Чемпіони_світу_зі_сноубордингу", "id": 800442}, {"name": "Футбольні_змагання_національних_збірних", "id": 1321535}, {"name": "Тур_ATP", "id": 1349783}, {"name": "Тенісні_турніри_на_кортах_з_твердим_покриттям", "id": 4000827}, {"name": "Хокей_із_шайбою_на_Олімпійських_іграх", "id": 1353485}, {"name": "Чемпіони_світу_з_фігурного_катання", "id": 979433}, {"name": "Матчі_СРСР_—_США_з_легкої_атлетики", "id": 4253000}, {"name": "Сноубордисти_на_зимових_Олімпійських_іграх_2010", "id": 800402}, {"name": "Чемпіони_світу_з_бадмінтону", "id": 1339792}, {"name": "Чемпіонати_світу_з_біатлону", "id": 1254063}, {"name": "Лижники_на_зимових_Олімпійських_іграх_2010", "id": 800760}, {"name": "Лижники_на_зимових_Олімпійських_іграх_2006", "id": 879990}, {"name": "Лижники_на_зимових_Олімпійських_іграх_1998", "id": 986888}, {"name": "Лижники_на_зимових_Олімпійських_іграх_2002", "id": 986889}, {"name": "Лижники_на_зимових_Олімпійських_іграх_2014", "id": 1653475}, {"name": "Лижники_на_зимових_Олімпійських_іграх_2018", "id": 3423371}, {"name": "Лижники_на_зимових_Олімпійських_іграх_2022", "id": 4440902}, {"name": "Бобслеїсти_на_зимових_Олімпійських_іграх_2010", "id": 801708}, {"name": "Бобслеїсти_на_зимових_Олімпійських_іграх_2014", "id": 2561285}, {"name": "Бобслеїсти_на_зимових_Олімпійських_іграх_2018", "id": 2660658}, {"name": "Чемпіони_світу_з_фристайлу", "id": 802599}, {"name": "Снукеристи,_що_зробили_100_і_більше_сенчурі-брейків", "id": 1104961}, {"name": "Футбольні_легіонери_в_Україні", "id": 972107}, {"name": "Футбольні_легіонери_в_Італії", "id": 972118}, {"name": "Футбольні_легіонери_в_Англії", "id": 972119}, {"name": "Футбольні_легіонери_в_Австрії", "id": 972134}, {"name": "Футбольні_легіонери_на_Кіпрі", "id": 972137}, {"name": "Футбольні_легіонери_в_Іспанії", "id": 972154}, {"name": "Футбольні_легіонери_в_Японії", "id": 1066490}, {"name": "Футбольні_легіонери_в_Ізраїлі", "id": 1068315}, {"name": "Футбольні_легіонери_у_Франції", "id": 1126332}, {"name": "Футбольні_легіонери_в_Азербайджані", "id": 1136581}, {"name": "Футбольні_легіонери_в_Бельгії", "id": 1284717}, {"name": "Футбольні_легіонери_в_Португалії", "id": 1284719}, {"name": "Футбольні_легіонери_в_Нідерландах", "id": 1284720}, {"name": "Футбольні_легіонери_в_Німеччині", "id": 1286730}, {"name": "Футбольні_легіонери_в_Росії", "id": 1286739}, {"name": "Футбольні_легіонери_в_Чехії", "id": 1286740}, {"name": "Футбольні_легіонери_в_Польщі", "id": 1286745}, {"name": "Футбольні_легіонери_в_Шотландії", "id": 1286767}, {"name": "Футбольні_легіонери_в_Австралії", "id": 1286771}, {"name": "Футбольні_легіонери_в_Аргентині", "id": 1287676}, {"name": "Футбольні_легіонери_в_Уельсі", "id": 1288083}, {"name": "Футбольні_легіонери_в_Румунії", "id": 1288141}, {"name": "Футбольні_легіонери_у_Вірменії", "id": 1288142}, {"name": "Футбольні_легіонери_в_Білорусі", "id": 1288143}, {"name": "Футбольні_легіонери_в_Латвії", "id": 1288157}, {"name": "Футбольні_легіонери_в_Естонії", "id": 1288163}, {"name": "Футбольні_легіонери_у_Фінляндії", "id": 1288165}, {"name": "Футбольні_легіонери_в_Уругваї", "id": 1289229}, {"name": "Футбольні_легіонери_в_Сербії", "id": 1290995}, {"name": "Футбольні_легіонери_в_Туреччині", "id": 1290996}, {"name": "Футбольні_легіонери_в_Мексиці", "id": 1291096}, {"name": "Футбольні_легіонери_в_Казахстані", "id": 1292050}, {"name": "Футбольні_легіонери_в_Китаї", "id": 1292057}, {"name": "Футбольні_легіонери_в_Південній_Кореї", "id": 1292061}, {"name": "Футбольні_легіонери_в_Болгарії", "id": 1292071}, {"name": "Футбольні_легіонери_в_Тунісі", "id": 1292073}, {"name": "Футбольні_легіонери_в_Саудівській_Аравії", "id": 1292075}, {"name": "Футбольні_легіонери_в_ОАЕ", "id": 1292077}, {"name": "Футбольні_легіонери_в_Норвегії", "id": 1292078}, {"name": "Футбольні_легіонери_в_Молдові", "id": 1292080}, {"name": "Футбольні_легіонери_в_Парагваї", "id": 1292082}, {"name": "Футбольні_легіонери_в_Канаді", "id": 1292083}, {"name": "Футбольні_легіонери_в_Єгипті", "id": 1292090}, {"name": "Футбольні_легіонери_на_Мальті", "id": 1292094}, {"name": "Футбольні_легіонери_в_Литві", "id": 1293470}, {"name": "Футбольні_легіонери_в_Узбекистані", "id": 1293471}, {"name": "Футбольні_легіонери_в_Ірані", "id": 1294070}, {"name": "Футбольні_легіонери_в_Угорщині", "id": 1294557}, {"name": "Футбольні_легіонери_в_Ісландії", "id": 1301123}, {"name": "Футбольні_легіонери_у_Бразилії", "id": 1308901}, {"name": "Футбольні_легіонери_у_Греції", "id": 1308903}, {"name": "Футбольні_легіонери_у_Словаччині", "id": 1308905}, {"name": "Футбольні_легіонери_у_Словенії", "id": 1308906}, {"name": "Футбольні_легіонери_у_США", "id": 1308907}, {"name": "Футбольні_легіонери_у_Швейцарії", "id": 1308911}, {"name": "Футбольні_легіонери_в_Катарі", "id": 1313846}, {"name": "Футбольні_легіонери_в_Данії", "id": 1313847}, {"name": "Футбольні_легіонери_в_Хорватії", "id": 1316063}, {"name": "Футбольні_легіонери_у_Швеції", "id": 1318084}, {"name": "Футбольні_легіонери_в_Чилі", "id": 1321355}, {"name": "Футбольні_легіонери_в_Ірландії", "id": 1324241}, {"name": "Футбольні_легіонери_в_Албанії", "id": 1337750}, {"name": "Футбольні_легіонери_в_Північній_Македонії", "id": 1458891}, {"name": "Футбольні_легіонери_в_Боснії_і_Герцеговині", "id": 1458894}, {"name": "Футбольні_легіонери_в_ПАР", "id": 1485313}, {"name": "Футбольні_легіонери_в_Лівані", "id": 1493064}, {"name": "Футбольні_легіонери_в_Кувейті", "id": 1546676}, {"name": "Футбольні_легіонери_в_Марокко", "id": 1559980}, {"name": "Футбольні_легіонери_у_В'єтнамі", "id": 1590840}, {"name": "Футбольні_легіонери_в_Гонконгу", "id": 1635471}, {"name": "Футбольні_легіонери_в_Новій_Зеландії", "id": 1682192}, {"name": "Футбольні_легіонери_в_Малайзії", "id": 1701071}, {"name": "Футбольні_легіонери_в_Колумбії", "id": 1709228}, {"name": "Футбольні_легіонери_в_Грузії", "id": 1712704}, {"name": "Футбольні_легіонери_в_Індії", "id": 1917586}, {"name": "Футбольні_легіонери_в_Індонезії", "id": 1925127}, {"name": "Футбольні_легіонери_в_Таїланді", "id": 1970588}, {"name": "Футбольні_легіонери_в_Еквадорі", "id": 2046618}, {"name": "Футбольні_легіонери_в_Люксембурзі", "id": 2046621}, {"name": "Футбольні_легіонери_в_Сінгапурі", "id": 2046624}, {"name": "Футбольні_легіонери_в_Таджикистані", "id": 2230251}, {"name": "Футбольні_легіонери_в_Коста-Риці", "id": 2248642}, {"name": "Футбольні_легіонери_в_Перу", "id": 2256500}, {"name": "Футбольні_легіонери_в_Болівії", "id": 2259466}, {"name": "Футбольні_легіонери_в_Чорногорії", "id": 2271308}, {"name": "Футбольні_легіонери_у_Гватемалі", "id": 2374762}, {"name": "Футбольні_легіонери_у_Венесуелі", "id": 2415736}, {"name": "Футбольні_легіонери_в_Чехословаччині", "id": 2421977}, {"name": "Футбольні_легіонери_в_Бангладеш", "id": 2973700}, {"name": "Українські_футбольні_легіонери", "id": 972101}, {"name": "Польські_футбольні_легіонери", "id": 972113}, {"name": "Італійські_футбольні_легіонери", "id": 972128}, {"name": "Радянські_футбольні_легіонери", "id": 972130}, {"name": "Бразильські_футбольні_легіонери", "id": 972158}, {"name": "Аргентинські_футбольні_легіонери", "id": 972160}, {"name": "Сербські_футбольні_легіонери", "id": 972162}, {"name": "Румунські_футбольні_легіонери", "id": 1286732}, {"name": "Німецькі_футбольні_легіонери", "id": 1286772}, {"name": "Чеські_футбольні_легіонери", "id": 1286778}, {"name": "Чилійські_футбольні_легіонери", "id": 1287666}, {"name": "Парагвайські_футбольні_легіонери", "id": 1287687}, {"name": "Тринідадські_футбольні_легіонери", "id": 1288055}, {"name": "Литовські_футбольні_легіонери", "id": 1288138}, {"name": "Російські_футбольні_легіонери", "id": 1288199}, {"name": "Молдовські_футбольні_легіонери", "id": 1288204}, {"name": "Португальські_футбольні_легіонери", "id": 1288613}, {"name": "Шведські_футбольні_легіонери", "id": 1291079}, {"name": "Хорватські_футбольні_легіонери", "id": 1291540}, {"name": "Нігерійські_футбольні_легіонери", "id": 1291676}, {"name": "Іспанські_футбольні_легіонери", "id": 1292048}, {"name": "Австрійські_футбольні_легіонери", "id": 1292051}, {"name": "Словацькі_футбольні_легіонери", "id": 1292070}, {"name": "Грузинські_футбольні_легіонери", "id": 1292079}, {"name": "Перуанські_футбольні_легіонери", "id": 1292084}, {"name": "Нідерландські_футбольні_легіонери", "id": 1292085}, {"name": "Болгарські_футбольні_легіонери", "id": 1292086}, {"name": "Фінські_футбольні_легіонери", "id": 1292088}, {"name": "Французькі_футбольні_легіонери", "id": 1292089}, {"name": "Гвінейські_футбольні_легіонери", "id": 1292092}, {"name": "Ганські_футбольні_легіонери", "id": 1292093}, {"name": "Вірменські_футбольні_легіонери", "id": 1292095}, {"name": "Шотландські_футбольні_легіонери", "id": 1292517}, {"name": "Білоруські_футбольні_легіонери", "id": 1293823}, {"name": "Азербайджанські_футбольні_легіонери", "id": 1294072}, {"name": "Грецькі_футбольні_легіонери", "id": 1294076}, {"name": "Латвійські_футбольні_легіонери", "id": 1294253}, {"name": "Угорські_футбольні_легіонери", "id": 1294621}, {"name": "Ізраїльські_футбольні_легіонери", "id": 1295972}, {"name": "Англійські_футбольні_легіонери", "id": 1296690}, {"name": "Івуарійські_футбольні_легіонери", "id": 1296715}, {"name": "Ірландські_футбольні_легіонери", "id": 1296719}, {"name": "Австралійські_футбольні_легіонери", "id": 1296725}, {"name": "Данські_футбольні_легіонери", "id": 1296727}, {"name": "Уругвайські_футбольні_легіонери", "id": 1296732}, {"name": "Колумбійські_футбольні_легіонери", "id": 1299084}, {"name": "Швейцарські_футбольні_легіонери", "id": 1300665}, {"name": "Албанські_футбольні_легіонери", "id": 1301497}, {"name": "Бельгійські_футбольні_легіонери", "id": 1302799}, {"name": "Ісландські_футбольні_легіонери", "id": 1304636}, {"name": "Боснійські_футбольні_легіонери", "id": 1305960}, {"name": "Сенегальські_футбольні_легіонери", "id": 1308152}, {"name": "Камерунські_футбольні_легіонери", "id": 1308553}, {"name": "Македонські_футбольні_легіонери", "id": 1316061}, {"name": "Мексиканські_футбольні_легіонери", "id": 1318803}, {"name": "Японські_футбольні_легіонери", "id": 1319259}, {"name": "Чорногорські_футбольні_легіонери", "id": 1333590}, {"name": "Чехословацькі_футбольні_легіонери", "id": 1333603}, {"name": "Словенські_футбольні_легіонери", "id": 1355557}, {"name": "Марокканські_футбольні_легіонери", "id": 1357731}, {"name": "Югославські_футбольні_легіонери", "id": 1362113}, {"name": "Малійські_футбольні_легіонери", "id": 1363297}, {"name": "Турецькі_футбольні_легіонери", "id": 1367226}, {"name": "Естонські_футбольні_легіонери", "id": 1381305}, {"name": "Норвезькі_футбольні_легіонери", "id": 1458889}, {"name": "Костариканські_футбольні_легіонери", "id": 1477059}, {"name": "Замбійські_футбольні_легіонери", "id": 1485309}, {"name": "Південноафриканські_футбольні_легіонери", "id": 1488365}, {"name": "Кабовердійські_футбольні_легіонери", "id": 1489431}, {"name": "Алжирські_футбольні_легіонери", "id": 1489439}, {"name": "Туніські_футбольні_легіонери", "id": 1489441}, {"name": "Буркінійські_футбольні_легіонери", "id": 1490482}, {"name": "Тоголезькі_футбольні_легіонери", "id": 1491072}, {"name": "Болівійські_футбольні_легіонери", "id": 1548446}, {"name": "Футбольні_легіонери_ДР_Конго", "id": 1567791}, {"name": "Футбольні_легіонери_США", "id": 1635289}, {"name": "Узбецькі_футбольні_легіонери", "id": 1669906}, {"name": "Гондураські_футбольні_легіонери", "id": 1697548}, {"name": "Іранські_футбольні_легіонери", "id": 1705227}, {"name": "Еквадорські_футбольні_легіонери", "id": 1708366}, {"name": "Південнокорейські_футбольні_легіонери", "id": 1736262}, {"name": "Казахські_футбольні_легіонери", "id": 1780219}, {"name": "Північноірландські_футбольні_легіонери", "id": 1887920}, {"name": "Футбольні_легіонери_Республіки_Конго", "id": 1987900}, {"name": "Єгипетські_футбольні_легіонери", "id": 2137241}, {"name": "Канадські_футбольні_легіонери", "id": 2169168}, {"name": "Гаїтянські_футбольні_легіонери", "id": 2217875}, {"name": "Киргизькі_футбольні_легіонери", "id": 2220704}, {"name": "Венесуельські_футбольні_легіонери", "id": 2245871}, {"name": "Панамські_футбольні_легіонери", "id": 2248640}, {"name": "Ямайські_футбольні_легіонери", "id": 2255912}, {"name": "Косовські_футбольні_легіонери", "id": 2302083}, {"name": "Гвінея-бісауські_футбольні_легіонери", "id": 2343973}, {"name": "Ангольські_футбольні_легіонери", "id": 2435441}, {"name": "Новозеландські_футбольні_легіонери", "id": 2446918}, {"name": "Кіпрські_футбольні_легіонери", "id": 2451582}, {"name": "Люксембурзькі_футбольні_легіонери", "id": 2471086}, {"name": "Китайські_футбольні_легіонери", "id": 2485083}, {"name": "Намібійські_футбольні_легіонери", "id": 3128241}, {"name": "Кенійські_футбольні_легіонери", "id": 3379177}, {"name": "Кіберспортивні_дисципліни", "id": 1901760}, {"name": "Олімпійські_чемпіони_з_вільної_боротьби", "id": 1163104}, {"name": "Борці_вільного_стилю_на_літніх_Олімпійських_іграх_2008", "id": 1255603}, {"name": "Борці_вільного_стилю_на_літніх_Олімпійських_іграх_2004", "id": 1256038}, {"name": "Борці_вільного_стилю_на_літніх_Олімпійських_іграх_2000", "id": 1256039}, {"name": "Борці_вільного_стилю_на_літніх_Олімпійських_іграх_1996", "id": 1256040}, {"name": "Борці_вільного_стилю_на_літніх_Олімпійських_іграх_2012", "id": 1355161}, {"name": "Борці_вільного_стилю_на_літніх_Олімпійських_іграх_1988", "id": 1502057}, {"name": "Борці_вільного_стилю_на_літніх_Олімпійських_іграх_1992", "id": 2055551}, {"name": "Борці_вільного_стилю_на_літніх_Олімпійських_іграх_2016", "id": 2240526}, {"name": "Борці_вільного_стилю_на_літніх_Олімпійських_іграх_2020", "id": 4298635}, {"name": "Борці_вільного_стилю_на_літніх_Олімпійських_іграх_2024", "id": 5321738}, {"name": "Українські_борці_греко-римського_стилю", "id": 381198}, {"name": "Грузинські_борці_греко-римського_стилю", "id": 1255630}, {"name": "Болгарські_борці_греко-римського_стилю", "id": 1256030}, {"name": "Радянські_борці_греко-римського_стилю", "id": 1342220}, {"name": "Вірменські_борці_греко-римського_стилю", "id": 1501813}, {"name": "Російські_борці_греко-римського_стилю", "id": 1502061}, {"name": "Казахські_борці_греко-римського_стилю", "id": 1503612}, {"name": "Іранські_борці_греко-римського_стилю", "id": 1503966}, {"name": "Борці_греко-римського_стилю_США", "id": 1504372}, {"name": "Південнокорейські_борці_греко-римського_стилю", "id": 1505403}, {"name": "Турецькі_борці_греко-римського_стилю", "id": 1506035}, {"name": "Угорські_борці_греко-римського_стилю", "id": 1512236}, {"name": "Перегонові_відеоігри", "id": 5174853}, {"name": "Академічне_веслування_на_Олімпійських_іграх", "id": 1334315}, {"name": "Олімпійські_чемпіони_з_бадмінтону", "id": 1160066}, {"name": "Бадмінтоністи_на_літніх_Олімпійських_іграх_2008", "id": 781655}, {"name": "Бадмінтоністи_на_літніх_Олімпійських_іграх_1996", "id": 781656}, {"name": "Бадмінтоністи_на_літніх_Олімпійських_іграх_2000", "id": 781658}, {"name": "Бадмінтоністи_на_літніх_Олімпійських_іграх_2004", "id": 781659}, {"name": "Бадмінтоністи_на_літніх_Олімпійських_іграх_2012", "id": 2215743}, {"name": "Бадмінтоністи_на_літніх_Олімпійських_іграх_2016", "id": 2334598}, {"name": "Бадмінтоністи_на_літніх_Олімпійських_іграх_2020", "id": 4308096}, {"name": "Фехтувальники_на_літніх_Олімпійських_іграх_2008", "id": 972762}, {"name": "Олімпійські_чемпіони_з_фехтування", "id": 974397}, {"name": "Фехтувальники_на_літніх_Олімпійських_іграх_2004", "id": 1028459}, {"name": "Фехтувальники_на_літніх_Олімпійських_іграх_2000", "id": 1028460}, {"name": "Фехтувальники_на_літніх_Олімпійських_іграх_2012", "id": 1349771}, {"name": "Фехтувальники_на_літніх_Олімпійських_іграх_1996", "id": 1835981}, {"name": "Фехтувальники_на_літніх_Олімпійських_іграх_1992", "id": 2160448}, {"name": "Фехтувальники_на_літніх_Олімпійських_іграх_1988", "id": 2160453}, {"name": "Фехтувальники_на_літніх_Олімпійських_іграх_1980", "id": 2160455}, {"name": "Фехтувальники_на_літніх_Олімпійських_іграх_1972", "id": 2160457}, {"name": "Фехтувальники_на_літніх_Олімпійських_іграх_1976", "id": 2160458}, {"name": "Фехтувальники_на_літніх_Олімпійських_іграх_1968", "id": 2160461}, {"name": "Фехтувальники_на_літніх_Олімпійських_іграх_1964", "id": 2160463}, {"name": "Фехтувальники_на_літніх_Олімпійських_іграх_1960", "id": 2160464}, {"name": "Фехтувальники_на_літніх_Олімпійських_іграх_2016", "id": 2232354}, {"name": "Фехтувальники_на_літніх_Олімпійських_іграх_1984", "id": 2450451}, {"name": "Фехтувальники_на_літніх_Олімпійських_іграх_2020", "id": 4297482}, {"name": "Фехтувальники_на_літніх_Олімпійських_іграх_2024", "id": 5321745}, {"name": "Відкритий_чемпіонат_США_з_тенісу", "id": 202840}, {"name": "Відкритий_чемпіонат_Австралії_з_тенісу", "id": 401132}, {"name": "Вімблдонський_турнір", "id": 494180}, {"name": "Відкритий_чемпіонат_Франції_з_тенісу", "id": 989208}, {"name": "Саночники_на_зимових_Олімпійських_іграх_2006", "id": 982410}, {"name": "Саночники_на_зимових_Олімпійських_іграх_2010", "id": 982411}, {"name": "Саночники_на_зимових_Олімпійських_іграх_2014", "id": 1647175}, {"name": "Саночники_на_зимових_Олімпійських_іграх_2018", "id": 2716387}, {"name": "Саночники_на_зимових_Олімпійських_іграх_2022", "id": 4440507}, {"name": "Фігуристи_на_зимових_Олімпійських_іграх_2010", "id": 636326}, {"name": "Олімпійські_чемпіони_з_фігурного_катання", "id": 983443}, {"name": "Фігуристи_на_зимових_Олімпійських_іграх_2006", "id": 986938}, {"name": "Фігуристи_на_зимових_Олімпійських_іграх_2002", "id": 986939}, {"name": "Фігуристи_на_зимових_Олімпійських_іграх_2014", "id": 1655968}, {"name": "Фігуристи_на_зимових_Олімпійських_іграх_1998", "id": 1848086}, {"name": "Фігуристи_на_зимових_Олімпійських_іграх_2018", "id": 2651867}, {"name": "Фігуристи_на_зимових_Олімпійських_іграх_2022", "id": 4453763}, {"name": "Олімпійські_чемпіони_з_хокею_на_траві", "id": 5230122}, {"name": "Хокеїсти_на_траві_на_літніх_Олімпійських_іграх_1980", "id": 1355791}, {"name": "Хокеїсти_на_траві_на_літніх_Олімпійських_іграх_2016", "id": 2873099}, {"name": "Хокеїсти_на_траві_на_літніх_Олімпійських_іграх_2000", "id": 2885947}, {"name": "Хокеїсти_на_траві_на_літніх_Олімпійських_іграх_2008", "id": 2885948}, {"name": "Хокеїсти_на_траві_на_літніх_Олімпійських_іграх_2004", "id": 2885949}, {"name": "Хокеїсти_на_траві_на_літніх_Олімпійських_іграх_2012", "id": 2885952}, {"name": "Хокеїсти_на_траві_на_літніх_Олімпійських_іграх_1988", "id": 5230128}, {"name": "Хокеїсти_на_траві_на_літніх_Олімпійських_іграх_1996", "id": 5230129}, {"name": "Хокеїсти_на_траві_на_літніх_Олімпійських_іграх_1992", "id": 5230130}, {"name": "Хокеїсти_на_траві_на_літніх_Олімпійських_іграх_1984", "id": 5230195}, {"name": "Хокеїсти_на_траві_на_літніх_Олімпійських_іграх_1952", "id": 5230223}, {"name": "Хокеїсти_на_траві_на_літніх_Олімпійських_іграх_1956", "id": 5230224}, {"name": "Олімпійські_чемпіони_зі_штовхання_ядра", "id": 2232396}, {"name": "Олімпійські_чемпіони_з_греко-римської_боротьби", "id": 1255619}, {"name": "Борці_греко-римського_стилю_на_літніх_Олімпійських_іграх_2008", "id": 1256042}, {"name": "Борці_греко-римського_стилю_на_літніх_Олімпійських_іграх_2004", "id": 1256043}, {"name": "Борці_греко-римського_стилю_на_літніх_Олімпійських_іграх_2012", "id": 1501802}, {"name": "Борці_греко-римського_стилю_на_літніх_Олімпійських_іграх_2000", "id": 1506585}, {"name": "Борці_греко-римського_стилю_на_літніх_Олімпійських_іграх_1996", "id": 1506587}, {"name": "Борці_греко-римського_стилю_на_літніх_Олімпійських_іграх_1992", "id": 1506588}, {"name": "Борці_греко-римського_стилю_на_літніх_Олімпійських_іграх_1988", "id": 1513840}, {"name": "Борці_греко-римського_стилю_на_літніх_Олімпійських_іграх_2016", "id": 2240529}, {"name": "Борці_греко-римського_стилю_на_літніх_Олімпійських_іграх_2020", "id": 4308818}, {"name": "Борці_греко-римського_стилю_на_літніх_Олімпійських_іграх_2024", "id": 5321737}, {"name": "Чемпіонат_світу_з_боротьби_2018", "id": 3052489}, {"name": "Чемпіонат_світу_з_боротьби_2019", "id": 3218093}, {"name": "Чемпіонат_світу_з_боротьби_2021", "id": 4361610}, {"name": "Чемпіонат_світу_з_боротьби_2022", "id": 4695490}, {"name": "Чемпіонат_світу_з_боротьби_2023", "id": 5053796}, {"name": "Українські_тренери_з_боротьби", "id": 2027376}, {"name": "Російські_тренери_з_боротьби", "id": 2035096}, {"name": "Тренери_з_боротьби_США", "id": 2219194}, {"name": "Олімпійські_чемпіони_з_бігу_на_100_метрів", "id": 1579444}, {"name": "Художні_гімнастки_на_літніх_Олімпійських_іграх_2012", "id": 2512148}, {"name": "Спортивні_гімнасти_на_літніх_Олімпійських_іграх_2012", "id": 2512165}, {"name": "Сноубордисти_на_зимових_Олімпійських_іграх_2014", "id": 1653480}, {"name": "Шорт-трековики_на_зимових_Олімпійських_іграх_2014", "id": 2702747}, {"name": "Шорт-трековики_на_зимових_Олімпійських_іграх_2006", "id": 3184661}, {"name": "Чемпіонати_світу_з_кросу", "id": 1923542}, {"name": "Мотогонщики_чемпіонату_світу_в_класі_MotoGP", "id": 1641642}, {"name": "Мотогонщики_чемпіонату_світу_в_класі_125cc", "id": 1641644}, {"name": "Мотогонщики_чемпіонату_світу_в_класі_Moto2", "id": 1641645}, {"name": "Мотогонщики_чемпіонату_світу_в_класі_250cc", "id": 1641648}, {"name": "Мотогонщики_чемпіонату_світу_в_класі_500cc", "id": 1641756}, {"name": "Українські_спортивні_ходоки", "id": 2771435}, {"name": "Літні_універсіади", "id": 1972739}, {"name": "Українські_біатлоністи", "id": 123022}, {"name": "Німецькі_біатлоністи", "id": 247920}, {"name": "Чорногорські_футболісти", "id": 1130987}, {"name": "Борчині_вільного_стилю_на_літніх_Олімпійських_іграх_2004", "id": 2464198}, {"name": "Уся_тематика_шахової_композиції_за_алфавітом", "id": 2200060}, {"name": "Ідеї_шахової_композиції_з_географічною_назвою", "id": 2616583}, {"name": "Ідеї,_виражені_в_задачах_на_прямий_мат", "id": 2667397}, {"name": "Ідеї,_виражені_в_задачах_на_кооперативний_мат", "id": 2667398}, {"name": "Ідеї,_складовою_яких_є_розв'язування_білих_фігур", "id": 2154131}, {"name": "Ідеї,_складовою_яких_є_зв'язування_білих_фігур", "id": 2154190}, {"name": "Ідеї,_складовою_яких_є_перекриття_чорних_фігур", "id": 2155287}, {"name": "Ідеї,_складовою_яких_є_розв'язування_чорних_фігур", "id": 2155842}, {"name": "Ідеї,_складовою_яких_є_зв'язування_чорних_фігур", "id": 2156738}, {"name": "Ідеї,_складовою_яких_є_чергування", "id": 2168736}, {"name": "Ідеї,_складовою_яких_є_загроза", "id": 2172507}, {"name": "Ідеї,_складовою_яких_є_тематичне_поле", "id": 2209100}, {"name": "Ідеї,_складовою_яких_є_переміна_функцій_ходу", "id": 2211444}, {"name": "Ідеї,_складовою_яких_є_хибні_сліди", "id": 2211947}, {"name": "Ідеї_шахової_композиції,_відкриті_в_Україні", "id": 1766571}, {"name": "Ідеї_шахової_композиції,_відкриті_в_Німеччині", "id": 2154452}, {"name": "Ідеї_шахової_композиції,_відкриті_в_Росії", "id": 2374520}, {"name": "Спортивні_гімнастки_на_літніх_Олімпійських_іграх_2016", "id": 2512157}, {"name": "Спортивні_гімнасти_на_літніх_Олімпійських_іграх_2016", "id": 2512162}, {"name": "Борчині_вільного_стилю_на_літніх_Олімпійських_іграх_2016", "id": 2464189}, {"name": "Команди_Формули-1", "id": 487390}, {"name": "Чемпіони_Європи_з_боксу", "id": 801876}, {"name": "Чемпіони_Європи_з_футболу", "id": 1027994}, {"name": "Чемпіони_Європи_з_плавання", "id": 1349439}, {"name": "Чемпіони_Європи_з_важкої_атлетики", "id": 1351527}, {"name": "Чемпіони_Європи_зі_спортивної_гімнастики", "id": 1860675}, {"name": "Чемпіони_Європи_з_легкої_атлетики", "id": 1927462}, {"name": "Чемпіонки_Європи_з_художньої_гімнастики", "id": 2157310}, {"name": "Чемпіони_Європи_з_фехтування", "id": 2160438}, {"name": "Чемпіони_Європи_з_академічного_веслування", "id": 2240258}, {"name": "Чемпіони_Європи_з_дзюдо", "id": 2475640}, {"name": "Чемпіони_Європи_з_баскетболу", "id": 2481687}, {"name": "Чемпіони_Азії_з_футболу", "id": 2916832}, {"name": "Чемпіони_Європи_з_легкої_атлетики_в_приміщенні", "id": 4138538}, {"name": "Чемпіони_Європи_з_водного_поло", "id": 4930333}, {"name": "Футбольні_клуби,_засновані_1903", "id": 1068570}, {"name": "Футбольні_клуби,_засновані_1964", "id": 1068573}, {"name": "Футбольні_клуби,_засновані_1932", "id": 1068575}, {"name": "Футбольні_клуби,_засновані_1919", "id": 1068583}, {"name": "Футбольні_клуби,_засновані_1904", "id": 1068606}, {"name": "Футбольні_клуби,_засновані_1905", "id": 1068607}, {"name": "Футбольні_клуби,_засновані_2005", "id": 1068610}, {"name": "Футбольні_клуби,_засновані_2000", "id": 1068694}, {"name": "Футбольні_клуби,_засновані_2001", "id": 1068695}, {"name": "Футбольні_клуби,_засновані_1936", "id": 1068696}, {"name": "Футбольні_клуби,_засновані_2006", "id": 1068697}, {"name": "Футбольні_клуби,_засновані_1996", "id": 1068703}, {"name": "Футбольні_клуби,_засновані_1955", "id": 1068708}, {"name": "Футбольні_клуби,_засновані_1923", "id": 1068709}, {"name": "Футбольні_клуби,_засновані_2011", "id": 1068710}, {"name": "Футбольні_клуби,_засновані_1965", "id": 1068712}, {"name": "Футбольні_клуби,_засновані_1998", "id": 1068715}, {"name": "Футбольні_клуби,_засновані_1995", "id": 1068718}, {"name": "Футбольні_клуби,_засновані_1930", "id": 1068719}, {"name": "Футбольні_клуби,_засновані_1927", "id": 1068720}, {"name": "Футбольні_клуби,_засновані_1993", "id": 1068721}, {"name": "Футбольні_клуби,_засновані_1958", "id": 1068722}, {"name": "Футбольні_клуби,_засновані_1950", "id": 1068725}, {"name": "Футбольні_клуби,_засновані_2009", "id": 1068728}, {"name": "Футбольні_клуби,_засновані_1957", "id": 1068729}, {"name": "Футбольні_клуби,_засновані_1946", "id": 1068730}, {"name": "Футбольні_клуби,_засновані_1960", "id": 1068732}, {"name": "Футбольні_клуби,_засновані_1997", "id": 1068734}, {"name": "Футбольні_клуби,_засновані_1925", "id": 1068735}, {"name": "Футбольні_клуби,_засновані_1924", "id": 1068736}, {"name": "Футбольні_клуби,_засновані_1989", "id": 1068737}, {"name": "Футбольні_клуби,_засновані_2004", "id": 1068738}, {"name": "Футбольні_клуби,_засновані_1992", "id": 1068739}, {"name": "Футбольні_клуби,_засновані_1908", "id": 1068740}, {"name": "Футбольні_клуби,_засновані_2002", "id": 1068741}, {"name": "Футбольні_клуби,_засновані_2008", "id": 1068933}, {"name": "Футбольні_клуби,_засновані_1940", "id": 1068934}, {"name": "Футбольні_клуби,_засновані_1928", "id": 1068936}, {"name": "Футбольні_клуби,_засновані_2007", "id": 1068937}, {"name": "Футбольні_клуби,_засновані_1948", "id": 1068945}, {"name": "Футбольні_клуби,_засновані_1922", "id": 1068953}, {"name": "Футбольні_клуби,_засновані_1999", "id": 1068966}, {"name": "Футбольні_клуби,_засновані_1947", "id": 1069022}, {"name": "Футбольні_клуби,_засновані_1935", "id": 1069025}, {"name": "Футбольні_клуби,_засновані_2003", "id": 1069027}, {"name": "Футбольні_клуби,_засновані_1920", "id": 1069028}, {"name": "Футбольні_клуби,_засновані_1991", "id": 1069037}, {"name": "Футбольні_клуби,_засновані_1906", "id": 1069052}, {"name": "Футбольні_клуби,_засновані_1909", "id": 1069054}, {"name": "Футбольні_клуби,_засновані_1962", "id": 1069057}, {"name": "Футбольні_клуби,_засновані_1931", "id": 1069068}, {"name": "Футбольні_клуби,_засновані_1949", "id": 1069070}, {"name": "Футбольні_клуби,_засновані_1911", "id": 1069074}, {"name": "Футбольні_клуби,_засновані_2010", "id": 1069076}, {"name": "Футбольні_клуби,_засновані_1910", "id": 1069082}, {"name": "Футбольні_клуби,_засновані_1926", "id": 1069084}, {"name": "Футбольні_клуби,_засновані_1969", "id": 1069105}, {"name": "Футбольні_клуби,_засновані_1907", "id": 1069120}, {"name": "Футбольні_клуби,_засновані_1990", "id": 1069123}, {"name": "Футбольні_клуби,_засновані_1914", "id": 1069125}, {"name": "Футбольні_клуби,_засновані_1913", "id": 1069127}, {"name": "Футбольні_клуби,_засновані_1929", "id": 1069130}, {"name": "Футбольні_клуби,_засновані_1967", "id": 1069135}, {"name": "Футбольні_клуби,_засновані_1912", "id": 1069144}, {"name": "Футбольні_клуби,_засновані_1937", "id": 1069293}, {"name": "Футбольні_клуби,_засновані_1921", "id": 1069338}, {"name": "Футбольні_клуби,_засновані_1945", "id": 1069350}, {"name": "Футбольні_клуби,_засновані_1966", "id": 1069440}, {"name": "Футбольні_клуби,_засновані_1968", "id": 1069441}, {"name": "Футбольні_клуби,_засновані_1994", "id": 1069443}, {"name": "Футбольні_клуби,_засновані_1953", "id": 1069452}, {"name": "Футбольні_клуби,_засновані_1970", "id": 1069467}, {"name": "Футбольні_клуби,_засновані_2013", "id": 1563572}, {"name": "Футбольні_клуби,_засновані_2012", "id": 1563583}, {"name": "Футбольні_клуби,_засновані_2014", "id": 1908909}, {"name": "Футбольні_клуби,_засновані_2015", "id": 2029772}, {"name": "Футбольні_клуби,_засновані_2016", "id": 2175633}, {"name": "Футбольні_клуби,_засновані_2017", "id": 2717347}, {"name": "Шахові_тренери", "id": 1333986}, {"name": "Футбольні_тренерки", "id": 5282852}, {"name": "Українські_хокейні_тренери", "id": 698005}, {"name": "Російські_хокейні_тренери", "id": 776596}, {"name": "Американські_хокейні_тренери", "id": 870844}, {"name": "Канадські_хокейні_тренери", "id": 870847}, {"name": "Радянські_хокейні_тренери", "id": 1101835}, {"name": "Чехословацькі_хокейні_тренери", "id": 1423031}, {"name": "Чемпіонки_світу_з_футболу", "id": 2190486}, {"name": "Гравчині_чемпіонату_світу_з_футболу_2015", "id": 2190384}, {"name": "Гравчині_чемпіонату_світу_з_футболу_2011", "id": 2190495}, {"name": "Гравчині_чемпіонату_світу_з_футболу_2007", "id": 2191641}, {"name": "Гравчині_збірної_України_з_футболу", "id": 2190434}, {"name": "Гравчині_збірної_Німеччини_з_футболу", "id": 2190506}, {"name": "Гравчині_збірної_Канади_з_футболу", "id": 2190818}, {"name": "Гравчині_збірної_Японії_з_футболу", "id": 2190974}, {"name": "Гравчині_збірної_Білорусі_з_футболу", "id": 3059036}, {"name": "Гравчині_збірної_Росії_з_футболу", "id": 4525988}, {"name": "Гравчині_збірної_Польщі_з_футболу", "id": 4531856}, {"name": "Чемпіони_Азії_з_греко-римської_боротьби", "id": 2172628}, {"name": "Чемпіони_Азії_з_вільної_боротьби", "id": 2174507}, {"name": "Чемпіонки_Азії_з_жіночої_боротьби", "id": 2464401}, {"name": "Теми_в_шаховій_композиції", "id": 1594742}, {"name": "Чемпіони_світу_з_вільної_боротьби", "id": 1127658}, {"name": "Чемпіони_Європи_з_вільної_боротьби", "id": 1982335}, {"name": "Чемпіони_Африки_з_вільної_боротьби", "id": 2311121}, {"name": "Панамериканські_чемпіони_з_вільної_боротьби", "id": 2353282}, {"name": "Чемпіони_Панамериканських_ігор_з_вільної_боротьби", "id": 2353302}, {"name": "Чемпіони_Азійських_ігор_з_вільної_боротьби", "id": 2446723}, {"name": "Чемпіони_світу_з_греко-римської_боротьби", "id": 1256041}, {"name": "Чемпіони_Європи_з_греко-римської_боротьби", "id": 1982291}, {"name": "Панамериканські_чемпіони_з_греко-римської_боротьби", "id": 2353584}, {"name": "Чемпіони_Панамериканських_ігор_з_греко-римської_боротьби", "id": 2353720}, {"name": "Чемпіони_Азійських_ігор_з_греко-римської_боротьби", "id": 2446713}, {"name": "Чемпіони_світу_з_дзюдо", "id": 701299}, {"name": "Олімпійські_чемпіони_з_дзюдо", "id": 802390}, {"name": "Олімпійські_чемпіони_з_веслування_на_байдарках_і_каное", "id": 1285549}, {"name": "Веслувальники_на_байдарках_і_каное_на_літніх_Олімпійських_іграх_2008", "id": 1285909}, {"name": "Веслувальники_на_байдарках_і_каное_на_літніх_Олімпійських_іграх_2004", "id": 1285911}, {"name": "Веслувальники_на_байдарках_і_каное_на_літніх_Олімпійських_іграх_1988", "id": 1353682}, {"name": "Веслувальники_на_байдарках_і_каное_на_літніх_Олімпійських_іграх_1992", "id": 1353690}, {"name": "Веслувальники_на_байдарках_і_каное_на_літніх_Олімпійських_іграх_1996", "id": 1353692}, {"name": "Веслувальники_на_байдарках_і_каное_на_літніх_Олімпійських_іграх_2000", "id": 1353696}, {"name": "Веслувальники_на_байдарках_і_каное_на_літніх_Олімпійських_іграх_2012", "id": 1981812}, {"name": "Веслувальники_на_байдарках_і_каное_на_літніх_Олімпійських_іграх_2016", "id": 2242200}, {"name": "Веслувальники_на_байдарках_і_каное_на_літніх_Олімпійських_іграх_2020", "id": 4301383}, {"name": "Спортивна_гімнастика_на_Олімпійських_іграх", "id": 2512056}, {"name": "Чемпіони_світу_зі_спортивної_гімнастики", "id": 803865}, {"name": "Борчині_вільного_стилю_на_літніх_Олімпійських_іграх_2012", "id": 2464186}, {"name": "Борчині_вільного_стилю_на_літніх_Олімпійських_іграх_2008", "id": 2464196}, {"name": "Борчині_вільного_стилю_на_літніх_Олімпійських_іграх_2020", "id": 4310621}, {"name": "Борчині_вільного_стилю_на_літніх_Олімпійських_іграх_2024", "id": 5321739}, {"name": "Українські_дзюдоїстки", "id": 2478762}, {"name": "Рекордсмени_світу_з_плавання", "id": 2488172}, {"name": "Українські_спортивні_гімнасти", "id": 2512074}, {"name": "Спортивні_гімнасти_США", "id": 2522765}, {"name": "Японські_спортивні_гімнасти", "id": 2525596}, {"name": "Олімпійські_чемпіонки_зі_спортивної_гімнастики", "id": 2512007}, {"name": "Чемпіонки_світу_зі_спортивної_гімнастики", "id": 2512094}, {"name": "Чемпіони_світу_з_фехтування", "id": 974396}, {"name": "Сноубордисти_на_зимових_Олімпійських_іграх_2018", "id": 2655425}, {"name": "Шорт-трековики_на_зимових_Олімпійських_іграх_2018", "id": 2655410}, {"name": "Олімпійські_чемпіони_з_метання_диска", "id": 2241470}, {"name": "Олімпійські_чемпіони_з_бігу_на_800_метрів", "id": 2232215}, {"name": "Призери_Ігор_Співдружності_з_легкої_атлетики", "id": 2578431}, {"name": "Легкоатлети_на_Іграх_Співдружності_2014", "id": 5183065}, {"name": "Легкоатлети_на_Іграх_Співдружності_2022", "id": 5183800}, {"name": "Легкоатлети_на_Іграх_Співдружності_2018", "id": 5183801}, {"name": "Чемпіонати_Європи_з_легкої_атлетики", "id": 808121}, {"name": "Чемпіонати_Європи_з_легкої_атлетики_в_приміщенні", "id": 2658708}, {"name": "Фристайлісти_на_зимових_Олімпійських_іграх_2010", "id": 802475}, {"name": "Олімпійські_чемпіони_з_фристайлу", "id": 802594}, {"name": "Фристайлісти_на_зимових_Олімпійських_іграх_2014", "id": 2036146}, {"name": "Фристайлісти_на_зимових_Олімпійських_іграх_2018", "id": 2651566}, {"name": "Фристайлісти_на_зимових_Олімпійських_іграх_2022", "id": 4452128}, {"name": "Чемпіонат_світу_з_фристайлу_та_сноубордингу_2023", "id": 4847381}, {"name": "Списки_найкращих_легкоатлетів_України", "id": 3010212}, {"name": "Списки_призерів_чемпіонатів_Європи_з_легкої_атлетики", "id": 2768429}, {"name": "Списки_призерів_чемпіонатів_СРСР_з_легкої_атлетики", "id": 3018509}, {"name": "Списки_призерів_чемпіонатів_світу_з_легкої_атлетики", "id": 3181498}, {"name": "Списки_призерів_чемпіонатів_України_з_легкої_атлетики", "id": 3190317}, {"name": "Списки_призерів_чемпіонатів_світу_з_легкої_атлетики_в_приміщенні", "id": 3387619}, {"name": "Списки_призерів_Олімпійських_ігор_з_легкої_атлетики", "id": 3485199}, {"name": "Списки_призерів_чемпіонатів_України_з_легкої_атлетики_в_приміщенні", "id": 3523367}, {"name": "Призери_чемпіонатів_світу_з_легкої_атлетики", "id": 4018983}, {"name": "Призери_чемпіонатів_світу_з_легкої_атлетики_в_приміщенні", "id": 4056110}, {"name": "Призери_чемпіонатів_світу_з_легкої_атлетики_серед_юніорів", "id": 4018321}, {"name": "Чемпіони_світу_з_естафетного_бігу_4×100_метрів", "id": 3210836}, {"name": "Чемпіони_світу_з_естафетного_бігу_4×400_метрів", "id": 3210872}, {"name": "Змагання_на_Чемпіонаті_світу_з_легкої_атлетики_2019", "id": 3157912}, {"name": "Стрибки_у_воду_на_Олімпійських_іграх", "id": 1350031}, {"name": "Олімпійські_чемпіони_з_марафонського_бігу", "id": 2232252}, {"name": "Чемпіони_світу_з_дартсу", "id": 2995638}, {"name": "Олімпійські_чемпіони_з_шорт-треку", "id": 2650117}, {"name": "Шорт-трековики_на_зимових_Олімпійських_іграх_2010", "id": 3184624}, {"name": "Шорт-трековики_на_зимових_Олімпійських_іграх_2022", "id": 4440890}, {"name": "Чемпіони_СРСР_з_легкої_атлетики", "id": 2388808}, {"name": "Чемпіони_світу_з_легкої_атлетики_серед_юнаків", "id": 2756403}, {"name": "Чемпіони_Європи_з_легкої_атлетики_серед_юніорів", "id": 2759280}, {"name": "Чемпіони_Європи_з_легкої_атлетики_серед_молоді", "id": 3247944}, {"name": "Призери_чемпіонатів_Європи_з_легкої_атлетики", "id": 3257942}, {"name": "Чемпіони_Універсіад_з_легкої_атлетики", "id": 3360499}, {"name": "Призери_Африканських_ігор_з_легкої_атлетики", "id": 4018612}, {"name": "Призери_чемпіонатів_Європи_з_легкої_атлетики_в_приміщенні", "id": 4138542}, {"name": "Призери_Азійських_ігор_з_легкої_атлетики", "id": 5333798}, {"name": "Олімпійські_чемпіони_з_бігу_на_200_метрів", "id": 1580127}, {"name": "Олімпійські_чемпіони_з_бігу_на_400_метрів_з_бар'єрами", "id": 1580239}, {"name": "Олімпійські_чемпіони_зі_стрибків_у_довжину", "id": 1581270}, {"name": "Олімпійські_чемпіони_з_бігу_на_400_метрів", "id": 1582096}, {"name": "Олімпійські_чемпіони_з_потрійного_стрибку", "id": 2231687}, {"name": "Олімпійські_чемпіони_зі_стрибків_у_висоту", "id": 2231732}, {"name": "Олімпійські_чемпіони_з_бігу_на_1500_метрів", "id": 2232227}, {"name": "Олімпійські_чемпіони_з_бігу_на_5000_метрів", "id": 2232240}, {"name": "Олімпійські_чемпіони_з_бігу_на_3000_метрів_з_перешкодами", "id": 2232262}, {"name": "Олімпійські_чемпіони_зі_стрибків_з_жердиною", "id": 2232276}, {"name": "Олімпійські_чемпіони_з_естафетного_бігу_4×100_метрів", "id": 2232751}, {"name": "Олімпійські_чемпіони_з_естафетного_бігу_4×400_метрів", "id": 2233119}, {"name": "Олімпійські_чемпіони_з_метання_молота", "id": 2242111}, {"name": "Олімпійські_чемпіони_з_метання_списа", "id": 2242171}, {"name": "Олімпійські_чемпіони_з_ковзанярського_спорту", "id": 972135}, {"name": "Ковзанярі_на_зимових_Олімпійських_іграх_2010", "id": 973245}, {"name": "Ковзанярі_на_зимових_Олімпійських_іграх_2006", "id": 982404}, {"name": "Ковзанярі_на_зимових_Олімпійських_іграх_2014", "id": 1945689}, {"name": "Ковзанярі_на_зимових_Олімпійських_іграх_2022", "id": 4451938}, {"name": "Ковзанярі_на_зимових_Олімпійських_іграх_2018", "id": 4451939}, {"name": "Чемпіони_світу_з_ковзанярського_спорту", "id": 979440}, {"name": "Чемпіонати_Європи_з_художньої_гімнастики", "id": 4261955}, {"name": "Чемпіонки_світу_з_художньої_гімнастики", "id": 977935}, {"name": "Чемпіони_України_з_фігурного_катання", "id": 2235663}, {"name": "Плавчині_вільним_стилем", "id": 4335217}, {"name": "Плавчині_батерфляєм", "id": 4335274}, {"name": "Плавчині_кролем_на_спині", "id": 4335313}, {"name": "Плавчині_брасом", "id": 4335316}, {"name": "Українські_плавчині", "id": 3505430}, {"name": "Плавчині_США", "id": 3599482}, {"name": "Німецькі_плавчині", "id": 4281178}, {"name": "Китайські_плавчині", "id": 4283374}, {"name": "Австралійські_плавчині", "id": 4283401}, {"name": "Японські_плавчині", "id": 4283767}, {"name": "Угорські_плавчині", "id": 4283770}, {"name": "Британські_плавчині", "id": 4283903}, {"name": "Канадські_плавчині", "id": 4283918}, {"name": "Італійські_плавчині", "id": 4283937}, {"name": "Російські_плавчині", "id": 4284800}, {"name": "Шведські_плавчині", "id": 4284814}, {"name": "Шахові_олімпіади", "id": 843382}, {"name": "Бронзові_призери_командних_чемпіонатів_світу_зі_спортивної_ходьби", "id": 4043246}, {"name": "Переможці_командних_чемпіонатів_світу_зі_спортивної_ходьби", "id": 4056094}, {"name": "Срібні_призери_командних_чемпіонатів_світу_зі_спортивної_ходьби", "id": 4056106}, {"name": "Чемпіони_України_з_бадмінтону", "id": 4114715}, {"name": "Чемпіони_Азії_з_бадмінтону", "id": 5249747}, {"name": "Eastbourne_International", "id": 2680353}, {"name": "Rosmalen_Grass_Court_Championships", "id": 2680374}, {"name": "Birmingham_Classic_(теніс)", "id": 2767302}, {"name": "Призери_Панамериканських_ігор_з_плавання", "id": 4286259}, {"name": "Призери_Ігор_Співдружності_з_плавання", "id": 4286270}, {"name": "Призери_Універсіад_з_плавання", "id": 4286783}, {"name": "Призери_Ігор_Південно-Східної_Азії_з_плавання", "id": 4287142}, {"name": "Призери_Африканських_ігор_з_плавання", "id": 4287824}, {"name": "Призери_Азійських_ігор_з_плавання", "id": 4299934}, {"name": "Олімпійські_чемпіони_з_плавання", "id": 885015}, {"name": "Бронзові_олімпійські_медалісти_з_плавання", "id": 1614070}, {"name": "Срібні_олімпійські_медалісти_з_плавання", "id": 1614080}, {"name": "Чемпіони_світу_з_плавання", "id": 1120938}, {"name": "Чемпіони_Азійських_ігор_з_плавання", "id": 2446717}, {"name": "Чемпіони_Ігор_Співдружності_з_плавання", "id": 4463272}, {"name": "Чемпіони_Панамериканських_ігор_з_плавання", "id": 4908085}, {"name": "Лучники_на_літніх_Олімпійських_іграх_2020", "id": 4297864}, {"name": "Чемпіони_України_з_легкої_атлетики", "id": 1926176}, {"name": "Чемпіони_Великої_Британії_з_легкої_атлетики", "id": 4295218}, {"name": "Чемпіони_Росії_з_легкої_атлетики", "id": 4295247}, {"name": "Чемпіони_США_з_легкої_атлетики", "id": 4295253}, {"name": "Сноубордисти_на_зимових_Олімпійських_іграх_2022", "id": 4452790}, {"name": "Стрибуни_з_трампліна_на_зимових_Олімпійських_іграх_2014", "id": 1654104}, {"name": "Стрибуни_з_трампліна_на_зимових_Олімпійських_іграх_2018", "id": 2651175}, {"name": "Стрибуни_з_трампліна_на_зимових_Олімпійських_іграх_2022", "id": 4452272}, {"name": "Російські_біатлоністки", "id": 4569861}, {"name": "Українські_біатлоністки", "id": 4569866}, {"name": "Чемпіони_світу_з_водного_поло", "id": 2449214}, {"name": "Грецькі_ватерполісти", "id": 4587480}, {"name": "Іспанські_ватерполісти", "id": 4587482}, {"name": "Італійські_ватерполісти", "id": 4587487}, {"name": "Російські_ватерполісти", "id": 4587501}, {"name": "Радянські_ватерполісти", "id": 4587505}, {"name": "Угорські_ватерполісти", "id": 4587510}, {"name": "Сербські_ватерполісти", "id": 4587520}, {"name": "Хорватські_ватерполісти", "id": 4587524}, {"name": "Югославські_ватерполісти", "id": 4587526}, {"name": "Ватерполісти_США", "id": 4587547}, {"name": "Німецькі_ватерполісти", "id": 5267910}, {"name": "Ватерполісти_та_ватерполістки_на_літніх_Олімпійських_іграх_2004", "id": 834477}, {"name": "Ватерполісти_на_літніх_Олімпійських_іграх_1952", "id": 1356037}, {"name": "Ватерполісти_на_літніх_Олімпійських_іграх_1956", "id": 1356038}, {"name": "Ватерполісти_на_літніх_Олімпійських_іграх_1960", "id": 1356039}, {"name": "Ватерполісти_на_літніх_Олімпійських_іграх_1968", "id": 1356041}, {"name": "Ватерполісти_на_літніх_Олімпійських_іграх_1972", "id": 1356042}, {"name": "Ватерполісти_на_літніх_Олімпійських_іграх_1980", "id": 1356043}, {"name": "Ватерполісти_та_ватерполістки_на_літніх_Олімпійських_іграх_2008", "id": 2449206}, {"name": "Ватерполісти_та_ватерполістки_на_літніх_Олімпійських_іграх_2012", "id": 2449208}, {"name": "Ватерполісти_та_ватерполістки_на_літніх_Олімпійських_іграх_2016", "id": 2449209}, {"name": "Ватерполісти_на_літніх_Олімпійських_іграх_1924", "id": 2456370}, {"name": "Ватерполісти_та_ватерполістки_на_літніх_Олімпійських_іграх_2000", "id": 2645067}, {"name": "Ватерполісти_на_літніх_Олімпійських_іграх_1964", "id": 4114935}, {"name": "Ватерполісти_на_літніх_Олімпійських_іграх_1996", "id": 4181805}, {"name": "Ватерполісти_на_літніх_Олімпійських_іграх_1992", "id": 4709564}, {"name": "Ватерполісти_на_літніх_Олімпійських_іграх_1976", "id": 4841050}, {"name": "Ватерполісти_та_ватерполістки_на_літніх_Олімпійських_іграх_2020", "id": 4841202}, {"name": "Олімпійські_медалісти_з_водного_поло", "id": 5304689}, {"name": "Ватерполісти_на_літніх_Олімпійських_іграх_1988", "id": 5322715}, {"name": "Ватерполісти_та_ватерполістки_на_літніх_Олімпійських_іграх_2024", "id": 5343242}, {"name": "Австралійські_ватерполістки", "id": 4587458}, {"name": "Російські_ватерполістки", "id": 4587499}, {"name": "Ватерполістки_США", "id": 4587549}, {"name": "Футбольні_клуби_Іспанії", "id": 189886}, {"name": "Стадіони_Іспанії", "id": 376881}, {"name": "Футбольні_клуби_Італії", "id": 171109}, {"name": "Італійські_автогонщики", "id": 246693}, {"name": "Італійські_мотогонщики", "id": 600860}, {"name": "Змагання_з_легкої_атлетики_в_Італії", "id": 2760220}, {"name": "Американські_хокеїсти", "id": 517299}, {"name": "Хокеїсти_АХЛ", "id": 1660719}, {"name": "Футбольні_клуби_США", "id": 605574}, {"name": "Змагання_з_легкої_атлетики_у_США", "id": 2760477}, {"name": "Бігуни_на_короткі_дистанції_США", "id": 2007467}, {"name": "Стрибуни_в_довжину_США", "id": 2008111}, {"name": "Бігуни_з_бар'єрами_США", "id": 2459412}, {"name": "Афроамериканські_легкоатлети", "id": 2879307}, {"name": "Легкоатлетки_США", "id": 2881486}, {"name": "Волейболістки_США", "id": 2498142}, {"name": "Призери_чемпіонатів_Європи_з_академічного_веслування", "id": 5317627}, {"name": "Водне_поло_на_Олімпійських_іграх", "id": 1348227}, {"name": "Кубок_Шпенглера", "id": 1504645}, {"name": "Чемпіонати_світу_з_хокею_із_шайбою", "id": 624311}, {"name": "Меморіал_Івана_Глінки", "id": 1592127}, {"name": "Чемпіонати_світу_з_хокею_із_шайбою_серед_молодіжних_команд", "id": 1749275}, {"name": "Чемпіонати_Європи_з_хокею_із_шайбою", "id": 1750835}, {"name": "Чемпіонати_світу_з_хокею_із_шайбою_серед_жінок", "id": 1799819}, {"name": "Азійський_Кубок_Виклику_з_хокею_із_шайбою", "id": 1810588}, {"name": "Єврохокейтур", "id": 1814720}, {"name": "Московський_міжнародний_турнір_з_хокею", "id": 1814792}, {"name": "Кубок_Кар'яла", "id": 1815220}, {"name": "Шведські_хокейні_ігри", "id": 1815228}, {"name": "Чемпіонати_Європи_з_хокею_із_шайбою_серед_юніорів", "id": 2064823}, {"name": "Володарі_Кубка_Канади", "id": 1370556}, {"name": "Баскетбол_на_Олімпійських_іграх", "id": 1348234}, {"name": "Легка_атлетика_на_Олімпійських_іграх", "id": 1342199}, {"name": "Легка_атлетика_на_Універсіадах", "id": 3139397}, {"name": "Міжконтинентальний_кубок_(футбол)", "id": 2874981}, {"name": "Олімпійські_чемпіони_з_футболу", "id": 803813}, {"name": "Чемпіони_світу_з_футболу", "id": 977939}, {"name": "Переможці_Ліги_чемпіонів_УЄФА", "id": 1793595}, {"name": "Переможці_Ліги_Європи_УЄФА", "id": 2769526}, {"name": "Чемпіони_Азійських_ігор_з_футболу", "id": 5257795}, {"name": "Арбітри_чемпіонатів_світу_з_футболу", "id": 1158442}, {"name": "Арбітри_Суперкубка_УЄФА", "id": 2436713}, {"name": "Арбітри_Ліги_чемпіонів_УЄФА", "id": 2769487}, {"name": "Арбітри_Ліги_Європи_УЄФА", "id": 2769536}, {"name": "Футбольні_арбітри_на_Олімпійських_іграх", "id": 2769552}, {"name": "Арбітри_чемпіонату_Європи_з_футболу_2020", "id": 4269884}, {"name": "Стадіони_англійської_Прем'єр-ліги", "id": 2595885}, {"name": "Гравці_чемпіонату_світу_з_футболу_2006", "id": 108237}, {"name": "Гравці_чемпіонату_світу_з_футболу_2002", "id": 191512}, {"name": "Гравці_чемпіонату_світу_з_футболу_1998", "id": 191514}, {"name": "Гравці_чемпіонату_світу_з_футболу_1994", "id": 191515}, {"name": "Гравці_чемпіонату_світу_з_футболу_1990", "id": 191516}, {"name": "Гравці_чемпіонату_світу_з_футболу_1966", "id": 225094}, {"name": "Гравці_чемпіонату_світу_з_футболу_1982", "id": 235251}, {"name": "Гравці_чемпіонату_світу_з_футболу_1986", "id": 239507}, {"name": "Гравці_чемпіонату_світу_з_футболу_1978", "id": 259477}, {"name": "Гравці_чемпіонату_світу_з_футболу_1974", "id": 335194}, {"name": "Гравці_чемпіонату_світу_з_футболу_1970", "id": 335195}, {"name": "Гравці_чемпіонату_світу_з_футболу_1962", "id": 335197}, {"name": "Гравці_чемпіонату_світу_з_футболу_1954", "id": 339828}, {"name": "Гравці_чемпіонату_світу_з_футболу_1958", "id": 339830}, {"name": "Гравці_чемпіонату_світу_з_футболу_2010", "id": 746729}, {"name": "Гравці_чемпіонату_світу_з_футболу_1930", "id": 746765}, {"name": "Гравці_чемпіонату_світу_з_футболу_1934", "id": 777681}, {"name": "Гравці_чемпіонату_світу_з_футболу_1938", "id": 778530}, {"name": "Гравці_чемпіонату_світу_з_футболу_1950", "id": 779305}, {"name": "Гравці_чемпіонату_світу_з_футболу_2014", "id": 1697530}, {"name": "Гравці_чемпіонату_світу_з_футболу_2018", "id": 2721814}, {"name": "Гравці_чемпіонату_світу_з_футболу_2022", "id": 4719546}, {"name": "Гравці_чемпіонату_Європи_з_футболу_2004", "id": 191511}, {"name": "Гравці_чемпіонату_Європи_з_футболу_2000", "id": 191513}, {"name": "Гравці_чемпіонату_Європи_з_футболу_1996", "id": 226070}, {"name": "Гравці_чемпіонату_Європи_з_футболу_1988", "id": 239535}, {"name": "Гравці_чемпіонату_Європи_з_футболу_1992", "id": 239547}, {"name": "Гравці_чемпіонату_Європи_з_футболу_2008", "id": 306965}, {"name": "Гравці_чемпіонату_Європи_з_футболу_1960", "id": 387144}, {"name": "Гравці_чемпіонату_Європи_з_футболу_1984", "id": 428244}, {"name": "Гравці_чемпіонату_Європи_з_футболу_1964", "id": 472565}, {"name": "Гравці_чемпіонату_Європи_з_футболу_1976", "id": 508418}, {"name": "Гравці_чемпіонату_Європи_з_футболу_1972", "id": 508420}, {"name": "Гравці_чемпіонату_Європи_з_футболу_1980", "id": 605272}, {"name": "Гравці_чемпіонату_Європи_з_футболу_1968", "id": 778529}, {"name": "Гравці_чемпіонату_Європи_з_футболу_2012", "id": 1316291}, {"name": "Гравці_чемпіонату_Європи_з_футболу_2016", "id": 2180379}, {"name": "Гравці_чемпіонату_Європи_з_футболу_2020", "id": 4228692}, {"name": "Гравці_чемпіонату_Європи_з_футболу_2024", "id": 5250289}, {"name": "Футболісти_на_літніх_Олімпійських_іграх_1952", "id": 973967}, {"name": "Футболісти_на_літніх_Олімпійських_іграх_1956", "id": 973968}, {"name": "Футболісти_на_літніх_Олімпійських_іграх_1964", "id": 973994}, {"name": "Футболісти_на_літніх_Олімпійських_іграх_1968", "id": 973995}, {"name": "Футболісти_на_літніх_Олімпійських_іграх_1972", "id": 974047}, {"name": "Футболісти_на_літніх_Олімпійських_іграх_1976", "id": 974051}, {"name": "Футболісти_на_літніх_Олімпійських_іграх_1980", "id": 974053}, {"name": "Футболісти_на_літніх_Олімпійських_іграх_1988", "id": 974058}, {"name": "Футболісти_на_літніх_Олімпійських_іграх_1992", "id": 974060}, {"name": "Футболісти_на_літніх_Олімпійських_іграх_1996", "id": 974064}, {"name": "Футболісти_на_літніх_Олімпійських_іграх_2000", "id": 974068}, {"name": "Футболісти_на_літніх_Олімпійських_іграх_2004", "id": 974069}, {"name": "Футболісти_на_літніх_Олімпійських_іграх_2008", "id": 974070}, {"name": "Футболісти_на_літніх_Олімпійських_іграх_1920", "id": 974387}, {"name": "Футболісти_на_літніх_Олімпійських_іграх_1928", "id": 974388}, {"name": "Футболісти_на_літніх_Олімпійських_іграх_1984", "id": 1042933}, {"name": "Футболісти_на_літніх_Олімпійських_іграх_1960", "id": 1063294}, {"name": "Футболісти_на_літніх_Олімпійських_іграх_1948", "id": 1083839}, {"name": "Футболісти_на_літніх_Олімпійських_іграх_1924", "id": 1088318}, {"name": "Футболісти_на_літніх_Олімпійських_іграх_1936", "id": 1098504}, {"name": "Футболісти_на_літніх_Олімпійських_іграх_1912", "id": 1118931}, {"name": "Футболісти_на_літніх_Олімпійських_іграх_2012", "id": 1344361}, {"name": "Футболісти_на_літніх_Олімпійських_іграх_2016", "id": 2224084}, {"name": "Футболісти_на_літніх_Олімпійських_іграх_1908", "id": 2311909}, {"name": "Футболісти_на_літніх_Олімпійських_іграх_2020", "id": 4296856}, {"name": "Футболісти_на_літніх_Олімпійських_іграх_2024", "id": 5314353}, {"name": "Гравці_кубка_африканських_націй_2012", "id": 1242992}, {"name": "Гравці_кубка_африканських_націй_1998", "id": 1313883}, {"name": "Гравці_кубка_африканських_націй_2000", "id": 1313885}, {"name": "Гравці_кубка_африканських_націй_2002", "id": 1313886}, {"name": "Гравці_кубка_африканських_націй_2004", "id": 1313887}, {"name": "Гравці_кубка_африканських_націй_2006", "id": 1313888}, {"name": "Гравці_кубка_африканських_націй_2008", "id": 1313890}, {"name": "Гравці_кубка_африканських_націй_2010", "id": 1313892}, {"name": "Гравці_кубка_африканських_націй_1996", "id": 1313916}, {"name": "Гравці_кубка_африканських_націй_1992", "id": 1314180}, {"name": "Гравці_кубка_африканських_націй_1994", "id": 1314182}, {"name": "Гравці_кубка_африканських_націй_1984", "id": 1314281}, {"name": "Гравці_кубка_африканських_націй_1988", "id": 1314282}, {"name": "Гравці_кубка_африканських_націй_2013", "id": 1484366}, {"name": "Гравці_кубка_африканських_націй_1982", "id": 1701046}, {"name": "Гравці_кубка_африканських_націй_2015", "id": 1854508}, {"name": "Гравці_кубка_африканських_націй_1986", "id": 2007037}, {"name": "Гравці_кубка_африканських_націй_1990", "id": 2256000}, {"name": "Гравці_кубка_африканських_націй_2017", "id": 2338749}, {"name": "Гравці_кубка_африканських_націй_2019", "id": 3138509}, {"name": "Гравці_кубка_африканських_націй_1972", "id": 4107129}, {"name": "Гравці_кубка_африканських_націй_1978", "id": 4108066}, {"name": "Гравці_кубка_африканських_націй_1974", "id": 4112653}, {"name": "Гравці_кубка_африканських_націй_2021", "id": 4431654}, {"name": "Гравці_кубка_африканських_націй_2023", "id": 5144386}, {"name": "Гравці_розіграшу_Кубка_конфедерацій_з_футболу_2013", "id": 1555824}, {"name": "Гравці_розіграшу_Кубка_конфедерацій_з_футболу_1992", "id": 1555839}, {"name": "Гравці_розіграшу_Кубка_конфедерацій_з_футболу_1995", "id": 1555841}, {"name": "Гравці_розіграшу_Кубка_конфедерацій_з_футболу_1997", "id": 1556320}, {"name": "Гравці_розіграшу_Кубка_конфедерацій_з_футболу_1999", "id": 1556324}, {"name": "Гравці_розіграшу_Кубка_конфедерацій_з_футболу_2001", "id": 1556594}, {"name": "Гравці_розіграшу_Кубка_конфедерацій_з_футболу_2003", "id": 1556596}, {"name": "Гравці_розіграшу_Кубка_конфедерацій_з_футболу_2005", "id": 1556730}, {"name": "Гравці_розіграшу_Кубка_конфедерацій_з_футболу_2009", "id": 1556862}, {"name": "Гравці_розіграшу_Кубка_конфедерацій_з_футболу_2017", "id": 2444359}, {"name": "Гравці_Кубка_Азії_з_футболу_2011", "id": 1668777}, {"name": "Гравці_Кубка_Азії_з_футболу_2007", "id": 1668818}, {"name": "Гравці_Кубка_Азії_з_футболу_2004", "id": 1668831}, {"name": "Гравці_Кубка_Азії_з_футболу_2000", "id": 1668835}, {"name": "Гравці_Кубка_Азії_з_футболу_1996", "id": 1668837}, {"name": "Гравці_Кубка_Азії_з_футболу_2015", "id": 1855050}, {"name": "Гравці_Кубка_Азії_з_футболу_1992", "id": 2142732}, {"name": "Гравці_Кубка_Азії_з_футболу_1988", "id": 2193782}, {"name": "Гравці_Кубка_Азії_з_футболу_1984", "id": 2417638}, {"name": "Гравці_Кубка_Азії_з_футболу_1980", "id": 2417639}, {"name": "Гравці_Кубка_Азії_з_футболу_2019", "id": 3003782}, {"name": "Гравці_Кубка_Азії_з_футболу_2023", "id": 5152819}, {"name": "Гравці_кубка_націй_ОФК_з_футболу_2012", "id": 2218521}, {"name": "Гравці_кубка_націй_ОФК_з_футболу_2016", "id": 2468191}, {"name": "Гравці_кубка_націй_ОФК_з_футболу_2002", "id": 3765861}, {"name": "Тренери_чемпіонату_світу_з_футболу_1998", "id": 332988}, {"name": "Тренери_чемпіонату_світу_з_футболу_2002", "id": 332996}, {"name": "Тренери_чемпіонату_світу_з_футболу_2010", "id": 752165}, {"name": "Тренери_чемпіонату_світу_з_футболу_2014", "id": 1701212}, {"name": "Тренери_чемпіонату_світу_з_футболу_2018", "id": 2722272}, {"name": "Тренери_чемпіонату_світу_з_футболу_2022", "id": 4725769}, {"name": "Ліга_чемпіонів_КАФ", "id": 2052501}, {"name": "Рекопа_Південної_Америки", "id": 3027413}, {"name": "Чемпіонат_України_з_футболу_(склади_команд)", "id": 1321529}, {"name": "Панамериканські_чемпіонки_з_жіночої_боротьби", "id": 2464476}, {"name": "Футбольні_клуби_Мексики", "id": 1311403}, {"name": "Brisbane_International", "id": 2767275}, {"name": "Змагання_з_легкої_атлетики_у_Великій_Британії", "id": 2378226}, {"name": "Змагання_з_легкої_атлетики_у_Франції", "id": 2760208}, {"name": "Футбольні_молодіжні_збірні_у_Європі", "id": 4765900}, {"name": "Футбольні_юнацькі_збірні_у_Європі_(U-17)", "id": 4852343}, {"name": "Футбольні_юнацькі_збірні_у_Європі_(U-19)", "id": 4852357}, {"name": "Футбольні_юнацькі_збірні_у_Європі_(U-16)", "id": 5087399}, {"name": "Чемпіонати_світу_із_шахів", "id": 843379}, {"name": "Чемпіонати_України_із_шахів", "id": 1750630}, {"name": "Чемпіонати_СРСР_із_шахів", "id": 1954305}, {"name": "Чемпіонати_світу_із_шахів_серед_жінок", "id": 4851087}, {"name": "Чемпіонати_України_із_шахів_серед_жінок", "id": 4851092}, {"name": "Чемпіонати_УРСР_із_шахів_(жінки)", "id": 5218670}, {"name": "Тур_WTA", "id": 231156}, {"name": "Футболісти_«Олімпії»_(Тегусігальпа)", "id": 766745}, {"name": "Футболісти_«Марафона»", "id": 766749}, {"name": "Футболісти_«Мотагуа»", "id": 1699391}, {"name": "Тренери_ФК_«Спарта»_(Прага)", "id": 1316823}, {"name": "Футболісти_«Аль-Аглі»_(Дубай)", "id": 1567193}, {"name": "Футболісти_«Аль-Айна»", "id": 1643948}, {"name": "Футболісти_«Аль-Насра»_(Дубай)", "id": 1670536}, {"name": "Футболісти_«Аль-Вахди»_(Абу-Дабі)", "id": 1935656}, {"name": "Футболісти_«Аль-Джазіри»", "id": 1972245}, {"name": "Футболісти_«Аль-Васла»", "id": 2328124}, {"name": "Футболісти_«Шарджі»", "id": 2483567}, {"name": "Футболісти_«Ередіано»", "id": 1710152}, {"name": "Футболісти_«Сапрісси»", "id": 1710159}, {"name": "Футболісти_«Алахуеленсе»", "id": 1710172}, {"name": "Футболісти_«Вадуца»", "id": 2052371}, {"name": "Футболісти_«Болівара»", "id": 2212463}, {"name": "Футболісти_«Орієнте_Петролеро»", "id": 2218042}, {"name": "Футболісти_«Зе_Стронгест»", "id": 2218047}, {"name": "Сезони_ФК_«Карпати»_(Львів)", "id": 513267}, {"name": "Сезони_«Динамо»_(Київ)", "id": 777560}, {"name": "Сезони_ФК_«Дніпро»_(Дніпро)", "id": 1050753}, {"name": "Футболісти_«Аль-Кадісії»_(Кувейт)", "id": 2398046}, {"name": "Футболісти_«Альянси»_(Сан-Сальвадор)", "id": 2415673}, {"name": "Футболісти_ФАС", "id": 2415684}, {"name": "Суперкубок_Англії_з_футболу", "id": 1583212}, {"name": "Суперкубок_Німеччини_з_футболу", "id": 1986330}, {"name": "Суперкубок_Італії_з_футболу", "id": 1989918}, {"name": "Суперкубок_Бельгії_з_футболу", "id": 1990104}, {"name": "Суперкубок_Франції_з_футболу", "id": 1990199}, {"name": "Суперкубок_Туреччини_з_футболу", "id": 2000386}, {"name": "Суперкубок_Албанії_з_футболу", "id": 2107661}, {"name": "Суперкубок_Португалії_з_футболу", "id": 2109797}, {"name": "Суперкубок_Естонії_з_футболу", "id": 2112013}, {"name": "Суперкубок_Ізраїлю_з_футболу", "id": 2112360}, {"name": "Суперкубок_Ісландії_з_футболу", "id": 2113002}, {"name": "Суперкубок_Іспанії_з_футболу", "id": 2115447}, {"name": "Суперкубок_Нідерландів_з_футболу", "id": 2118184}, {"name": "Суперкубок_Польщі_з_футболу", "id": 2118592}, {"name": "Суперкубок_Сан-Марино_з_футболу", "id": 2118861}, {"name": "Суперкубок_Японії_з_футболу", "id": 4616241}, {"name": "Президенти_українських_футбольних_клубів", "id": 1958225}, {"name": "Президенти_ФК_«Депортіво_Алавес»", "id": 3142021}, {"name": "Чемпіонат_УРСР_з_футболу", "id": 970451}, {"name": "Перша_ліга_СРСР_з_футболу", "id": 4758241}, {"name": "Сезони_Вищої_ліги_СРСР_з_футболу", "id": 4758249}, {"name": "Фінали_Ліги_чемпіонів_УЄФА", "id": 721217}, {"name": "Фінали_Кубка_УЄФА", "id": 1335503}, {"name": "Фінали_Кубка_Футбольної_ліги", "id": 1646329}, {"name": "Фінали_Кубка_володарів_кубків_УЄФА", "id": 2617228}, {"name": "Фінали_кубка_Англії_з_футболу", "id": 1294585}, {"name": "Фінали_кубка_України_з_футболу", "id": 1764058}, {"name": "Фінали_Кубка_СРСР_з_футболу", "id": 2456909}, {"name": "Фінали_кубка_Німеччини_з_футболу", "id": 4630333}, {"name": "Фінали_кубка_Італії_з_футболу", "id": 4856641}, {"name": "Фінали_кубка_Іспанії_з_футболу", "id": 4856643}, {"name": "Матчі_ФК_«Шахтар»_(Донецьк)", "id": 2435195}, {"name": "Матчі_ФК_«Динамо»_(Київ)", "id": 2435196}, {"name": "Футбольні_клуби_Англії", "id": 124397}, {"name": "Футбольні_клуби_Франції", "id": 124426}, {"name": "Футбольні_клуби_Росії", "id": 125664}, {"name": "Футбольні_клуби_Німеччини", "id": 196082}, {"name": "Футбольні_клуби_Польщі", "id": 360204}, {"name": "Футбольні_клуби_Нідерландів", "id": 368691}, {"name": "Футбольні_клуби_Португалії", "id": 368795}, {"name": "Футбольні_клуби_Бельгії", "id": 369071}, {"name": "Футбольні_клуби_Румунії", "id": 369318}, {"name": "Футбольні_клуби_Шотландії", "id": 369661}, {"name": "Футбольні_клуби_Сербії", "id": 370489}, {"name": "Футбольні_клуби_Туреччини", "id": 380219}, {"name": "Футбольні_клуби_Білорусі", "id": 383315}, {"name": "Футбольні_клуби_Греції", "id": 384162}, {"name": "Футбольні_клуби_Грузії", "id": 384590}, {"name": "Футбольні_клуби_Чехії", "id": 390709}, {"name": "Футбольні_клуби_Болгарії", "id": 390714}, {"name": "Футбольні_клуби_Швейцарії", "id": 391039}, {"name": "Футбольні_клуби_Норвегії", "id": 398679}, {"name": "Футбольні_клуби_Данії", "id": 399977}, {"name": "Футбольні_клуби_Австрії", "id": 399989}, {"name": "Футбольні_клуби_Угорщини", "id": 400023}, {"name": "Футбольні_клуби_Хорватії", "id": 400597}, {"name": "Футбольні_клуби_Швеції", "id": 400773}, {"name": "Футбольні_клуби_Молдови", "id": 416589}, {"name": "Футбольні_клуби_Ізраїлю", "id": 439481}, {"name": "Футбольні_клуби_Литви", "id": 497647}, {"name": "Футбольні_клуби_Латвії", "id": 656916}, {"name": "Футбольні_клуби_Північної_Македонії", "id": 670117}, {"name": "Футбольні_клуби_Естонії", "id": 670158}, {"name": "Футбольні_клуби_Фінляндії", "id": 670176}, {"name": "Футбольні_клуби_Уельсу", "id": 670423}, {"name": "Футбольні_клуби_Люксембургу", "id": 670440}, {"name": "Футбольні_клуби_Боснії_і_Герцеговини", "id": 1532628}, {"name": "Футболісти_«Актобе»", "id": 548138}, {"name": "Футбольні_стадіони_України", "id": 2646641}, {"name": "Футбольні_стадіони_Німеччини", "id": 4862065}, {"name": "Легкоатлетичні_стадіони_України", "id": 2659319}, {"name": "Угандійські_футболісти", "id": 1490609}, {"name": "Українські_футболісти", "id": 46926}, {"name": "Французькі_футболісти", "id": 71181}, {"name": "Німецькі_футболісти", "id": 71182}, {"name": "Футболісти_Сан-Марино", "id": 71186}, {"name": "Бразильські_футболісти", "id": 71187}, {"name": "Швейцарські_футболісти", "id": 71188}, {"name": "Іспанські_футболісти", "id": 71189}, {"name": "Португальські_футболісти", "id": 71218}, {"name": "Чеські_футболісти", "id": 74574}, {"name": "Італійські_футболісти", "id": 77108}, {"name": "Англійські_футболісти", "id": 78942}, {"name": "Аргентинські_футболісти", "id": 104317}, {"name": "Російські_футболісти", "id": 109341}, {"name": "Ірландські_футболісти", "id": 123409}, {"name": "Футболісти_США", "id": 137284}, {"name": "Чехословацькі_футболісти", "id": 148434}, {"name": "Шведські_футболісти", "id": 151120}, {"name": "Радянські_футболісти", "id": 157724}, {"name": "Польські_футболісти", "id": 160636}, {"name": "Нігерійські_футболісти", "id": 189058}, {"name": "Грузинські_футболісти", "id": 211999}, {"name": "Румунські_футболісти", "id": 214667}, {"name": "Гвінейські_футболісти", "id": 220858}, {"name": "Білоруські_футболісти", "id": 221679}, {"name": "Мексиканські_футболісти", "id": 247083}, {"name": "Естонські_футболісти", "id": 267978}, {"name": "Сербські_футболісти", "id": 295820}, {"name": "Латвійські_футболісти", "id": 312400}, {"name": "Австрійські_футболісти", "id": 332978}, {"name": "Узбецькі_футболісти", "id": 355603}, {"name": "Бельгійські_футболісти", "id": 357617}, {"name": "Шотландські_футболісти", "id": 420025}, {"name": "Норвезькі_футболісти", "id": 422795}, {"name": "Угорські_футболісти", "id": 422796}, {"name": "Турецькі_футболісти", "id": 422956}, {"name": "Камерунські_футболісти", "id": 423598}, {"name": "Південноафриканські_футболісти", "id": 425336}, {"name": "Словенські_футболісти", "id": 425417}, {"name": "Хорватські_футболісти", "id": 462764}, {"name": "Грецькі_футболісти", "id": 501320}, {"name": "Чилійські_футболісти", "id": 509032}, {"name": "Кіпрські_футболісти", "id": 509943}, {"name": "Литовські_футболісти", "id": 510481}, {"name": "Югославські_футболісти", "id": 513022}, {"name": "Боснійські_футболісти", "id": 513083}, {"name": "Македонські_футболісти", "id": 513146}, {"name": "Уругвайські_футболісти", "id": 517910}, {"name": "Таджицькі_футболісти", "id": 519722}, {"name": "Вірменські_футболісти", "id": 547614}, {"name": "Фінські_футболісти", "id": 553564}, {"name": "Єгипетські_футболісти", "id": 556546}, {"name": "Нідерландські_футболісти", "id": 568522}, {"name": "Албанські_футболісти", "id": 584573}, {"name": "Марокканські_футболісти", "id": 596773}, {"name": "Данські_футболісти", "id": 610136}, {"name": "Болгарські_футболісти", "id": 640056}, {"name": "Парагвайські_футболісти", "id": 644867}, {"name": "Венесуельські_футболісти", "id": 645724}, {"name": "Алжирські_футболісти", "id": 650879}, {"name": "Молдовські_футболісти", "id": 674712}, {"name": "Люксембурзькі_футболісти", "id": 704171}, {"name": "Австралійські_футболісти", "id": 723467}, {"name": "Словацькі_футболісти", "id": 747892}, {"name": "Новозеландські_футболісти", "id": 753810}, {"name": "Північнокорейські_футболісти", "id": 759969}, {"name": "Киргизькі_футболісти", "id": 763450}, {"name": "Ганські_футболісти", "id": 766609}, {"name": "Гондураські_футболісти", "id": 766741}, {"name": "Південнокорейські_футболісти", "id": 768531}, {"name": "Азербайджанські_футболісти", "id": 780830}, {"name": "Болівійські_футболісти", "id": 781559}, {"name": "Перуанські_футболісти", "id": 781563}, {"name": "Ізраїльські_футболісти", "id": 825067}, {"name": "Колумбійські_футболісти", "id": 841519}, {"name": "Еквадорські_футболісти", "id": 918055}, {"name": "Японські_футболісти", "id": 921100}, {"name": "Валлійські_футболісти", "id": 945583}, {"name": "Північноірландські_футболісти", "id": 1038645}, {"name": "Сенегальські_футболісти", "id": 1051143}, {"name": "Костариканські_футболісти", "id": 1088828}, {"name": "Ісландські_футболісти", "id": 1088837}, {"name": "Малійські_футболісти", "id": 1145576}, {"name": "Ангольські_футболісти", "id": 1236110}, {"name": "Туніські_футболісти", "id": 1236150}, {"name": "Івуарійські_футболісти", "id": 1237386}, {"name": "Габонські_футболісти", "id": 1238354}, {"name": "Замбійські_футболісти", "id": 1241089}, {"name": "Футболісти_Екваторіальної_Гвінеї", "id": 1243755}, {"name": "Фарерські_футболісти", "id": 1244032}, {"name": "Тринідадські_футболісти", "id": 1284860}, {"name": "Казахські_футболісти", "id": 1367210}, {"name": "Канадські_футболісти", "id": 1449211}, {"name": "Кабовердійські_футболісти", "id": 1484963}, {"name": "Сальвадорські_футболісти", "id": 1488982}, {"name": "Тоголезькі_футболісти", "id": 1489989}, {"name": "Буркінійські_футболісти", "id": 1490481}, {"name": "Футболісти_ДР_Конго", "id": 1567406}, {"name": "Іранські_футболісти", "id": 1638828}, {"name": "Афганські_футболісти", "id": 1682247}, {"name": "Бутанські_футболісти", "id": 1758138}, {"name": "Іракські_футболісти", "id": 1783110}, {"name": "Мальтійські_футболісти", "id": 1789614}, {"name": "Гамбійські_футболісти", "id": 1789868}, {"name": "Футболісти_Республіки_Конго", "id": 1842464}, {"name": "Еміратські_футболісти", "id": 1855042}, {"name": "Китайські_футболісти", "id": 1857690}, {"name": "Саудівські_футболісти", "id": 1861489}, {"name": "Туркменські_футболісти", "id": 1875041}, {"name": "Кенійські_футболісти", "id": 2025502}, {"name": "Індонезійські_футболісти", "id": 2063120}, {"name": "Ямайські_футболісти", "id": 2191112}, {"name": "Гаїтянські_футболісти", "id": 2194470}, {"name": "Косовські_футболісти", "id": 2206653}, {"name": "Каталонські_футболісти", "id": 2216437}, {"name": "Панамські_футболісти", "id": 2218640}, {"name": "Гаянські_футболісти", "id": 2245118}, {"name": "Катарські_футболісти", "id": 2321394}, {"name": "Зімбабвійські_футболісти", "id": 2339740}, {"name": "Гвінея-бісауські_футболісти", "id": 2339745}, {"name": "Кувейтські_футболісти", "id": 2347652}, {"name": "Східнонімецькі_футболісти", "id": 2403455}, {"name": "Кубинські_футболісти", "id": 2449138}, {"name": "Ланкійські_футболісти", "id": 3016793}, {"name": "Намібійські_футболісти", "id": 3128234}, {"name": "Російські_хокеїсти", "id": 130828}, {"name": "Шведські_хокеїсти", "id": 151116}, {"name": "Радянські_хокеїсти", "id": 406058}, {"name": "Канадські_хокеїсти", "id": 507914}, {"name": "Українські_хокеїсти", "id": 516872}, {"name": "Словацькі_хокеїсти", "id": 621881}, {"name": "Білоруські_хокеїсти", "id": 633065}, {"name": "Чеські_хокеїсти", "id": 640482}, {"name": "Казахські_хокеїсти", "id": 643211}, {"name": "Латвійські_хокеїсти", "id": 653119}, {"name": "Фінські_хокеїсти", "id": 653492}, {"name": "Польські_хокеїсти", "id": 673279}, {"name": "Словенські_хокеїсти", "id": 677331}, {"name": "Австрійські_хокеїсти", "id": 681918}, {"name": "Чехословацькі_хокеїсти", "id": 683732}, {"name": "Німецькі_хокеїсти", "id": 708817}, {"name": "Норвезькі_хокеїсти", "id": 840254}, {"name": "Швейцарські_хокеїсти", "id": 866787}, {"name": "Українські_боксери", "id": 54272}, {"name": "Боксери_США", "id": 421550}, {"name": "Польські_боксери", "id": 737162}, {"name": "Британські_боксери", "id": 797803}, {"name": "Німецькі_боксери", "id": 804512}, {"name": "Радянські_боксери", "id": 804555}, {"name": "Узбецькі_боксери", "id": 815604}, {"name": "Кубинські_боксери", "id": 816185}, {"name": "Угорські_боксери", "id": 917752}, {"name": "Болгарські_боксери", "id": 917754}, {"name": "Російські_боксери", "id": 1077759}, {"name": "Французькі_боксери", "id": 1078570}, {"name": "Італійські_боксери", "id": 1127495}, {"name": "Ірландські_боксери", "id": 1293153}, {"name": "Південноафриканські_боксери", "id": 1354694}, {"name": "Казахські_боксери", "id": 1425303}, {"name": "Азербайджанські_боксери", "id": 1425308}, {"name": "Японські_боксери", "id": 1432320}, {"name": "Пуерториканські_боксери", "id": 1504182}, {"name": "Мексиканські_боксери", "id": 1577801}, {"name": "Румунські_боксери", "id": 1889744}, {"name": "Південнокорейські_боксери", "id": 2228813}, {"name": "Вірменські_боксери", "id": 2709442}, {"name": "Українські_шахісти", "id": 37665}, {"name": "Шахісти_США", "id": 137290}, {"name": "Ізраїльські_шахісти", "id": 204311}, {"name": "Французькі_шахісти", "id": 204600}, {"name": "Російські_шахісти", "id": 223887}, {"name": "Радянські_шахісти", "id": 293274}, {"name": "Німецькі_шахісти", "id": 428747}, {"name": "Угорські_шахісти", "id": 432034}, {"name": "Польські_шахісти", "id": 515393}, {"name": "Болгарські_шахісти", "id": 737268}, {"name": "Британські_шахісти", "id": 828410}, {"name": "Вірменські_шахісти", "id": 912459}, {"name": "Грузинські_шахісти", "id": 1294291}, {"name": "Румунські_шахісти", "id": 1887109}, {"name": "Сербські_шахісти", "id": 1989653}, {"name": "Югославські_шахісти", "id": 1989655}, {"name": "Хорватські_шахісти", "id": 2166654}, {"name": "Шахісти_Російської_імперії", "id": 2176647}, {"name": "Хорватські_гандболісти", "id": 1004654}, {"name": "Шведські_гандболісти", "id": 1456904}, {"name": "Російські_гандболістки", "id": 3491956}, {"name": "Італійські_фехтувальники", "id": 509909}, {"name": "Німецькі_фехтувальники", "id": 510031}, {"name": "Російські_фехтувальники", "id": 511321}, {"name": "Французькі_фехтувальники", "id": 957389}, {"name": "Фехтувальники_США", "id": 958396}, {"name": "Польські_фехтувальники", "id": 958513}, {"name": "Радянські_фехтувальники", "id": 1119818}, {"name": "Румунські_фехтувальники", "id": 1293219}, {"name": "Угорські_фехтувальники", "id": 1308406}, {"name": "Південнокорейські_фехтувальники", "id": 1420528}, {"name": "Німецькі_бобслеїсти", "id": 801704}, {"name": "Українські_яхтсмени", "id": 978015}, {"name": "Британські_яхтсмени", "id": 979642}, {"name": "Французькі_яхтсмени", "id": 979654}, {"name": "Яхтсмени_США", "id": 979969}, {"name": "Австралійські_яхтсмени", "id": 979985}, {"name": "Данські_яхтсмени", "id": 980640}, {"name": "Німецькі_яхтсмени", "id": 980653}, {"name": "Шведські_яхтсмени", "id": 980933}, {"name": "Норвезькі_яхтсмени", "id": 1955099}, {"name": "Німецькі_веслувальники_на_байдарках_і_каное", "id": 978280}, {"name": "Українські_веслувальники_на_байдарках_і_каное", "id": 1285857}, {"name": "Радянські_веслувальники_на_байдарках_і_каное", "id": 1286683}, {"name": "Німецькі_хокеїсти_на_траві", "id": 1085160}, {"name": "Британські_хокеїсти_на_траві", "id": 1447946}, {"name": "Австралійські_хокеїсти_на_траві", "id": 1449931}, {"name": "Нідерландські_хокеїсти_на_траві", "id": 1450245}, {"name": "Індійські_хокеїсти_на_траві", "id": 2303020}, {"name": "Бельгійські_хокеїсти_на_траві", "id": 2753558}, {"name": "Західнонімецькі_хокеїсти_на_траві", "id": 5276080}, {"name": "Пакистанські_хокеїсти_на_траві", "id": 5276097}, {"name": "Іспанські_хокеїсти_на_траві", "id": 5276115}, {"name": "Російські_борці_вільного_стилю", "id": 1499220}, {"name": "Російські_борчині_вільного_стилю", "id": 2464212}, {"name": "Борці_вільного_стилю_США", "id": 1504371}, {"name": "Борчині_вільного_стилю_США", "id": 2465181}, {"name": "Американські_реслери", "id": 3818252}, {"name": "Японські_борці_вільного_стилю", "id": 1504092}, {"name": "Японські_борчині_вільного_стилю", "id": 2468366}, {"name": "Грузинські_борці_вільного_стилю", "id": 1255614}, {"name": "Турецькі_борці_вільного_стилю", "id": 1506037}, {"name": "Китайські_борчині_вільного_стилю", "id": 2464999}, {"name": "Канадські_борці_вільного_стилю", "id": 1507712}, {"name": "Канадські_борчині_вільного_стилю", "id": 2464993}, {"name": "Українські_борці_вільного_стилю", "id": 1255599}, {"name": "Азербайджанські_борці_вільного_стилю", "id": 1255624}, {"name": "Болгарські_борці_вільного_стилю", "id": 1256029}, {"name": "Радянські_борці_вільного_стилю", "id": 1342241}, {"name": "Індійські_борці_вільного_стилю", "id": 1501953}, {"name": "Іранські_борці_вільного_стилю", "id": 1503824}, {"name": "Угорські_борці_вільного_стилю", "id": 1512272}, {"name": "Українські_стрільці", "id": 352299}, {"name": "Українські_самбісти", "id": 1276136}, {"name": "Нідерландські_ковзанярі", "id": 889889}, {"name": "Шведські_керлінгісти", "id": 1662239}, {"name": "Українські_пауерліфтери", "id": 1843044}, {"name": "Радянські_хокеїсти_з_м'ячем", "id": 2290332}, {"name": "Українські_лижники", "id": 621996}, {"name": "Шведські_лижники", "id": 798914}, {"name": "Російські_лижники", "id": 879996}, {"name": "Австрійські_гірськолижники", "id": 663849}, {"name": "Німецькі_стрибуни_у_воду", "id": 974841}, {"name": "Українські_стрибуни_у_воду", "id": 974845}, {"name": "Китайські_стрибуни_у_воду", "id": 975075}, {"name": "Стрибуни_у_воду_США", "id": 1422889}, {"name": "Грецькі_олімпійські_ватерполісти_та_ватерполістки", "id": 5343285}, {"name": "Угорські_олімпійські_ватерполісти_та_ватерполістки", "id": 5343286}, {"name": "Олімпійські_ватерполісти_та_ватерполістки_США", "id": 5343466}, {"name": "Радянські_олімпійські_ватерполісти_та_ватерполістки", "id": 5343303}, {"name": "Російські_олімпійські_ватерполісти_та_ватерполістки", "id": 5343300}, {"name": "Югославські_олімпійські_ватерполісти_та_ватерполістки", "id": 5343471}, {"name": "Російські_тенісисти", "id": 189108}, {"name": "Чеські_тенісисти", "id": 195852}, {"name": "Бельгійські_тенісисти", "id": 196266}, {"name": "Німецькі_тенісисти", "id": 197126}, {"name": "Австралійські_тенісисти", "id": 228790}, {"name": "Іспанські_тенісисти", "id": 276510}, {"name": "Французькі_тенісисти", "id": 315030}, {"name": "Британські_тенісисти", "id": 335624}, {"name": "Аргентинські_тенісисти", "id": 384603}, {"name": "Радянські_тенісисти", "id": 385023}, {"name": "Італійські_тенісисти", "id": 399492}, {"name": "Тенісисти_США", "id": 421559}, {"name": "Хорватські_тенісисти", "id": 506074}, {"name": "Бразильські_тенісисти", "id": 507226}, {"name": "Австрійські_тенісисти", "id": 507814}, {"name": "Шведські_тенісисти", "id": 806071}, {"name": "Чилійські_тенісисти", "id": 1074765}, {"name": "Південноафриканські_тенісисти", "id": 1358977}, {"name": "Канадські_тенісисти", "id": 1578400}, {"name": "Нідерландські_тенісисти", "id": 2739478}, {"name": "Мексиканські_тенісисти", "id": 4570944}, {"name": "Англійські_тенісисти", "id": 4981264}, {"name": "Західнонімецькі_тенісисти", "id": 4981277}, {"name": "Німецькі_вершники", "id": 1027647}, {"name": "Вершники_США", "id": 1038634}, {"name": "Шведські_вершники", "id": 1293411}, {"name": "Французькі_вершники", "id": 3001168}, {"name": "Французькі_регбісти", "id": 1424096}, {"name": "Австрійські_стрибуни_з_трампліна", "id": 633412}, {"name": "Українські_пауерліфтерки", "id": 4955040}, {"name": "Західнонімецькі_тенісистки", "id": 4980825}, {"name": "Австралійські_олімпійські_плавці_та_плавчині", "id": 4990241}, {"name": "Австрійські_олімпійські_плавці_та_плавчині", "id": 4990252}, {"name": "Бельгійські_олімпійські_плавці_та_плавчині", "id": 4990261}, {"name": "Бразильські_олімпійські_плавці_та_плавчині", "id": 4990268}, {"name": "Олімпійські_плавці_та_плавчині_США", "id": 4990280}, {"name": "Канадські_олімпійські_плавці_та_плавчині", "id": 4990283}, {"name": "Китайські_олімпійські_плавці_та_плавчині", "id": 4990291}, {"name": "Данські_олімпійські_плавці_та_плавчині", "id": 4990309}, {"name": "Французькі_олімпійські_плавці_та_плавчині", "id": 4990354}, {"name": "Німецькі_олімпійські_плавці_та_плавчині", "id": 4990361}, {"name": "Західнонімецькі_олімпійські_плавці_та_плавчині", "id": 4990365}, {"name": "Британські_олімпійські_плавці_та_плавчині", "id": 4990367}, {"name": "Грецькі_олімпійські_плавці_та_плавчині", "id": 4990377}, {"name": "Угорські_олімпійські_плавці_та_плавчині", "id": 4990389}, {"name": "Італійські_олімпійські_плавці_та_плавчині", "id": 4990399}, {"name": "Японські_олімпійські_плавці_та_плавчині", "id": 4990408}, {"name": "Нідерландські_олімпійські_плавці_та_плавчині", "id": 4990450}, {"name": "Новозеландські_олімпійські_плавці_та_плавчині", "id": 4990455}, {"name": "Польські_олімпійські_плавці_та_плавчині", "id": 4990469}, {"name": "Російські_олімпійські_плавці_та_плавчині", "id": 4990476}, {"name": "Південноафриканські_олімпійські_плавці_та_плавчині", "id": 4990490}, {"name": "Радянські_олімпійські_плавці_та_плавчині", "id": 4990491}, {"name": "Іспанські_олімпійські_плавці_та_плавчині", "id": 4990493}, {"name": "Шведські_олімпійські_плавці_та_плавчині", "id": 4990500}, {"name": "Українські_олімпійські_плавці_та_плавчині", "id": 4990516}, {"name": "Східнонімецькі_олімпійські_плавці_та_плавчині", "id": 4990634}, {"name": "Теніс", "id": 161515}, {"name": "Вигадані_лучники", "id": 4997537}, {"name": "Стрільба_на_Олімпійських_іграх", "id": 1348805}, {"name": "Олімпійські_чемпіони_зі_стрілецького_спорту", "id": 1147934}, {"name": "Стрільці_на_літніх_Олімпійських_іграх_2008", "id": 1147939}, {"name": "Стрільці_на_літніх_Олімпійських_іграх_2000", "id": 1147965}, {"name": "Стрільці_на_літніх_Олімпійських_іграх_2004", "id": 1147967}, {"name": "Стрільці_на_літніх_Олімпійських_іграх_1996", "id": 1147971}, {"name": "Стрільці_на_літніх_Олімпійських_іграх_2012", "id": 1348949}, {"name": "Стрільці_на_літніх_Олімпійських_іграх_2016", "id": 2232467}, {"name": "Стрільці_на_літніх_Олімпійських_іграх_2020", "id": 4297711}, {"name": "Важкоатлети_на_літніх_Олімпійських_іграх_2008", "id": 351075}, {"name": "Важкоатлети_на_літніх_Олімпійських_іграх_2004", "id": 1034050}, {"name": "Важкоатлети_на_літніх_Олімпійських_іграх_2000", "id": 1337842}, {"name": "Важкоатлети_на_літніх_Олімпійських_іграх_1996", "id": 1337873}, {"name": "Важкоатлети_на_літніх_Олімпійських_іграх_2012", "id": 1350118}, {"name": "Важкоатлети_на_літніх_Олімпійських_іграх_1992", "id": 1513573}, {"name": "Важкоатлети_на_літніх_Олімпійських_іграх_1976", "id": 2085667}, {"name": "Важкоатлети_на_літніх_Олімпійських_іграх_2016", "id": 2232800}, {"name": "Важкоатлети_на_літніх_Олімпійських_іграх_1988", "id": 3175524}, {"name": "Важкоатлети_на_літніх_Олімпійських_іграх_1984", "id": 3175525}, {"name": "Важкоатлети_на_літніх_Олімпійських_іграх_2020", "id": 4298490}, {"name": "Важкоатлети_на_літніх_Олімпійських_іграх_1980", "id": 4961265}, {"name": "Важкоатлети_на_літніх_Олімпійських_іграх_1972", "id": 5250169}, {"name": "Олімпійські_медалісти_з_важкої_атлетики", "id": 5318085}, {"name": "Медалісти_чемпіонату_світу_з_важкої_атлетики", "id": 5318083}, {"name": "Олімпійські_чемпіони_з_важкої_атлетики", "id": 979352}, {"name": "Чемпіони_світу_з_важкої_атлетики", "id": 979355}, {"name": "Українські_борчині_вільного_стилю", "id": 2464226}, {"name": "Монгольські_борчині_вільного_стилю", "id": 2465059}, {"name": "Дзюдоїсти_на_літніх_Олімпійських_іграх_2020", "id": 4297384}, {"name": "Гравці_збірної_Нігерії_з_футболу", "id": 423410}, {"name": "Шаблони:Склади_збірної_Нігерії_з_футболу", "id": 763336}, {"name": "Гравці_молодіжної_збірної_Нігерії_з_футболу", "id": 1566695}, {"name": "Гравці_збірної_Алжиру_з_футболу", "id": 772415}, {"name": "Гравці_олімпійської_збірної_Алжиру_з_футболу", "id": 4372937}, {"name": "Призери_Ігор_Співдружності_з_боротьби", "id": 4463262}, {"name": "Плавці_та_плавчині_на_Іграх_Співдружності_1998", "id": 5181996}, {"name": "Плавці_та_плавчині_на_Іграх_Співдружності_2018", "id": 5185710}, {"name": "Чемпіони_Ігор_Співдружності_з_боротьби", "id": 4463261}, {"name": "Чемпіонки_світу_з_жіночої_боротьби", "id": 2464183}, {"name": "Чемпіонки_Європи_з_жіночої_боротьби", "id": 2464190}, {"name": "Тренери_українських_хокейних_клубів", "id": 3061677}, {"name": "Члени_зали_слави_хокею", "id": 624384}, {"name": "Олімпійські_чемпіони_з_хокею_із_шайбою", "id": 939927}, {"name": "Члени_Зали_слави_ІІХФ", "id": 960945}, {"name": "Чемпіони_світу_з_хокею", "id": 624365}, {"name": "Італійські_волейболісти", "id": 1445540}, {"name": "Волейболісти_італійських_клубів", "id": 4331626}, {"name": "Легкоатлети_на_Азійських_іграх_2018", "id": 5219346}, {"name": "Борці_на_Азійських_іграх_2022", "id": 5218621}, {"name": "Борці_на_Азійських_іграх_2018", "id": 5218638}, {"name": "Борці_на_Азійських_іграх_2014", "id": 5218961}, {"name": "Борці_на_Азійських_іграх_2010", "id": 5219149}, {"name": "Борці_на_Азійських_іграх_2006", "id": 5221510}, {"name": "Борці_на_Азійських_іграх_2002", "id": 5221600}, {"name": "Борці_на_Азійських_іграх_1998", "id": 5221601}, {"name": "Борці_на_Азійських_іграх_1994", "id": 5221721}, {"name": "Плавці_та_плавчині_на_Азійських_іграх_2002", "id": 5248637}, {"name": "Плавці_та_плавчині_на_Азійських_іграх_2006", "id": 5248639}, {"name": "Плавці_та_плавчині_на_Азійських_іграх_2010", "id": 5248641}, {"name": "Плавці_та_плавчині_на_Азійських_іграх_2014", "id": 5248643}, {"name": "Плавці_та_плавчині_на_Азійських_іграх_2018", "id": 5248644}, {"name": "Бадмінтоністи_на_Азійських_іграх_2010", "id": 5249320}, {"name": "Бадмінтоністи_на_Азійських_іграх_2014", "id": 5249321}, {"name": "Бадмінтоністи_на_Азійських_іграх_2018", "id": 5249322}, {"name": "Бельгійські_олімпійські_ватерполісти_та_ватерполістки", "id": 5343268}, {"name": "Хокеїсти_на_траві_—_півзахисники", "id": 5280010}, {"name": "Хокеїсти_на_траві_—_нападники", "id": 5280030}, {"name": "Західнонімецькі_хокеїстки_на_траві", "id": 5276081}, {"name": "Академічні_веслувальники_США", "id": 1285639}, {"name": "Італійські_академічні_веслувальники", "id": 1285651}, {"name": "Австралійські_академічні_веслувальники", "id": 1285654}, {"name": "Британські_академічні_веслувальники", "id": 1285802}, {"name": "Данські_академічні_веслувальники", "id": 1285809}, {"name": "Канадські_академічні_веслувальники", "id": 1285815}, {"name": "Нідерландські_академічні_веслувальники", "id": 1285824}, {"name": "Німецькі_академічні_веслувальники", "id": 1285829}, {"name": "Новозеландські_академічні_веслувальники", "id": 1285830}, {"name": "Польські_академічні_веслувальники", "id": 1285832}, {"name": "Українські_академічні_веслувальники", "id": 1285855}, {"name": "Французькі_академічні_веслувальники", "id": 1285892}, {"name": "Радянські_академічні_веслувальники", "id": 1286068}, {"name": "Норвезькі_академічні_веслувальники", "id": 2740729}, {"name": "Швейцарські_академічні_веслувальники", "id": 2741139}, {"name": "Російські_академічні_веслувальники", "id": 4300729}, {"name": "Олімпійські_чемпіони_з_академічного_веслування", "id": 1286224}, {"name": "Чемпіони_світу_з_академічного_веслування", "id": 1338440}, {"name": "Британські_академічні_веслувальниці", "id": 5283528}, {"name": "Канадські_академічні_веслувальниці", "id": 5283539}, {"name": "Китайські_академічні_веслувальниці", "id": 5283541}, {"name": "Нідерландські_академічні_веслувальниці", "id": 5283547}, {"name": "Німецькі_академічні_веслувальниці", "id": 5283550}, {"name": "Академічні_веслувальниці_США", "id": 5283568}, {"name": "Румунські_академічні_веслувальниці", "id": 5283569}, {"name": "Радянські_академічні_веслувальниці", "id": 5283576}, {"name": "Українські_академічні_веслувальниці", "id": 5283578}, {"name": "Східнонімецькі_академічні_веслувальники", "id": 5283611}, {"name": "Східнонімецькі_академічні_веслувальниці", "id": 5283612}, {"name": "Західнонімецькі_академічні_веслувальники", "id": 5283626}, {"name": "Олімпійські_медалісти_з_хокею_на_траві", "id": 5304636}, {"name": "Призери_Ігор_Співдружності_з_хокею_на_траві", "id": 5322108}, {"name": "Призери_Азійських_ігор_з_хокею_на_траві", "id": 5322419}, {"name": "Призери_Панамериканських_ігор_з_хокею_на_траві", "id": 5322420}, {"name": "Важкоатлети,_дискваліфіковані_за_вживання_допінгу", "id": 3779771}, {"name": "Українські_важкоатлети", "id": 350751}, {"name": "Радянські_важкоатлети", "id": 452586}, {"name": "Російські_важкоатлети", "id": 973499}, {"name": "Китайські_важкоатлети", "id": 974263}, {"name": "Німецькі_важкоатлети", "id": 1121464}, {"name": "Важкоатлети_США", "id": 2457206}, {"name": "Болгарські_важкоатлети", "id": 5296832}, {"name": "Рекордсмени_світу_з_важкої_атлетики", "id": 2488171}, {"name": "Призери_Азійських_ігор_з_важкої_атлетики", "id": 5318107}, {"name": "Українські_важкоатлетки", "id": 2550221}, {"name": "Італійські_олімпійські_ватерполісти_та_ватерполістки", "id": 5343287}, {"name": "Іспанські_олімпійські_ватерполісти_та_ватерполістки", "id": 5343306}, {"name": "Українські_бігуни_на_короткі_дистанції", "id": 1925064}, {"name": "Ямайські_бігуни_на_короткі_дистанції", "id": 2005324}, {"name": "Британські_бігуни_на_короткі_дистанції", "id": 2655542}, {"name": "Бігунки_на_короткі_дистанції_США", "id": 5347584}, {"name": "Німецькі_бігунки_на_короткі_дистанції", "id": 5347644}, {"name": "Радянські_бігунки_на_короткі_дистанції", "id": 5347651}, {"name": "Українські_бігунки_на_короткі_дистанції", "id": 5347666}, {"name": "Ямайські_бігунки_на_короткі_дистанції", "id": 5347679}, {"name": "Британські_бігунки_на_короткі_дистанції", "id": 5347606}, {"name": "Кенійські_бігуни_на_середні_дистанції", "id": 2005299}, {"name": "Українські_бігунки_на_середні_дистанції", "id": 5347793}, {"name": "Кенійські_бігуни_на_довгі_дистанції", "id": 1843017}, {"name": "Українські_бігунки_на_довгі_дистанції", "id": 5347898}, {"name": "Українські_легкоатлетки", "id": 2720068}, {"name": "Українські_олімпійські_легкоатлети_та_легкоатлетки", "id": 5350992}, {"name": "Українські_стрибунки_в_довжину", "id": 5347291}, {"name": "Австралійські_олімпійські_легкоатлети_та_легкоатлетки", "id": 5351628}, {"name": "Британські_олімпійські_легкоатлети_та_легкоатлетки", "id": 5351658}, {"name": "Китайські_олімпійські_легкоатлети_та_легкоатлетки", "id": 5351679}, {"name": "Ефіопські_олімпійські_легкоатлети_та_легкоатлетки", "id": 5351711}, {"name": "Фінські_олімпійські_легкоатлети_та_легкоатлетки", "id": 5351761}, {"name": "Французькі_олімпійські_легкоатлети_та_легкоатлетки", "id": 5351763}, {"name": "Східнонімецькі_олімпійські_легкоатлети_та_легкоатлетки", "id": 5351772}, {"name": "Німецькі_олімпійські_легкоатлети_та_легкоатлетки", "id": 5351774}, {"name": "Італійські_олімпійські_легкоатлети_та_легкоатлетки", "id": 5351809}, {"name": "Ямайські_олімпійські_легкоатлети_та_легкоатлетки", "id": 5351814}, {"name": "Кенійські_олімпійські_легкоатлети_та_легкоатлетки", "id": 5351823}, {"name": "Польські_олімпійські_легкоатлети_та_легкоатлетки", "id": 5351876}, {"name": "Російські_олімпійські_легкоатлети_та_легкоатлетки", "id": 5351886}, {"name": "Радянські_олімпійські_легкоатлети_та_легкоатлетки", "id": 5351902}, {"name": "Шведські_олімпійські_легкоатлети_та_легкоатлетки", "id": 5351911}, {"name": "Олімпійські_легкоатлети_та_легкоатлетки_США", "id": 5352032}, {"name": "Канадські_олімпійські_легкоатлети_та_легкоатлетки", "id": 5352079}, {"name": "Бронзові_призери_чемпіонатів_світу_з_боротьби", "id": 5380275}, {"name": "Срібні_призери_чемпіонатів_світу_з_боротьби", "id": 5380279}]}