{"name": "Новоісторична_Росія", "id": 2243153, "predecessors": [{"name": "Головна", "id": 13205}], "successors": [{"name": "Більшовики", "id": 287755}, {"name": "Революція_1905—1907", "id": 1274579}, {"name": "Історія_Російської_імперії", "id": 1642876}, {"name": "Московське_царство", "id": 2589032}, {"name": "Губернії_Російської_імперії_на_території_Росії", "id": 2773337}, {"name": "Міжнародні_угоди_Російської_імперії", "id": 1321158}, {"name": "Громадянська_війна_в_Росії", "id": 286496}, {"name": "Радянська_доба_Ростовської_області", "id": 2773756}]}