{"name": "Історія_Югославії", "id": 232046, "predecessors": [{"name": "Новітня_історія_Боснії_і_Герцеговини", "id": 2576687}, {"name": "Новітня_історія_Сербії", "id": 2576692}, {"name": "Новітня_історія_Хорватії", "id": 2576695}, {"name": "Земля", "id": 49013}, {"name": "Головна", "id": 13205}, {"name": "Історія_Європи", "id": 15739}], "successors": [{"name": "Югославія_в_Другій_світовій_війні", "id": 883209}, {"name": "Війна_за_незалежність_Хорватії", "id": 1038347}, {"name": "Боснійська_війна", "id": 1715776}]}