{"name": "Хрестові_походи", "id": 234089, "predecessors": [{"name": "Історія_Європи", "id": 15739}, {"name": "Історія_ісламу", "id": 450888}, {"name": "Католицизм", "id": 15030}, {"name": "Середньовічна_Європа", "id": 2588998}, {"name": "Історія_християнства", "id": 245870}, {"name": "Головна", "id": 13205}, {"name": "Військова_історія", "id": 620066}, {"name": "Земля", "id": 49013}, {"name": "Релігія", "id": 13456}], "successors": [{"name": "Держави_хрестоносців", "id": 156589}, {"name": "Хрестоносці", "id": 381610}]}