{"name": "Колишні_райони_Київської_області", "id": 2656629, "predecessors": [{"name": "Історія_Київської_області", "id": 452545}, {"name": "Історичний_територіальний_поділ_України", "id": 59075}, {"name": "Держава", "id": 33976}], "successors": [{"name": "Адміністративний_устрій_Сквирського_району", "id": 1721045}, {"name": "Адміністративний_устрій_Миронівського_району", "id": 1721049}, {"name": "Адміністративний_устрій_Переяслав-Хмельницького_району", "id": 1556570}, {"name": "Адміністративний_устрій_Кагарлицького_району", "id": 1721028}, {"name": "Колишні_населені_пункти_Поліського_району", "id": 1155897}]}