{"name": "Видавнича_справа", "id": 30138, "predecessors": [{"name": "Виробництво", "id": 35886}, {"name": "Головна", "id": 13205}], "successors": [{"name": "Поліграфія", "id": 22907}, {"name": "Видавці", "id": 33915}, {"name": "Друкарство", "id": 82869}, {"name": "Типографські_знаки", "id": 211981}, {"name": "Шрифти", "id": 262749}, {"name": "Зображення:Логотипи:Видавництва", "id": 3383587}, {"name": "Музичні_сайти", "id": 948284}, {"name": "Автори_підручників", "id": 3000332}, {"name": "Економічні_журнали", "id": 604274}, {"name": "Дитячі_книги", "id": 166217}, {"name": "Дитячі_журнали", "id": 278597}, {"name": "Феміністична_література", "id": 2742920}, {"name": "Журналістки", "id": 3696125}, {"name": "Політичні_журнали", "id": 623674}, {"name": "Журнали_з_культури", "id": 623668}, {"name": "Бібліографія", "id": 158480}, {"name": "Українські_поліграфісти", "id": 902455}, {"name": "Видавництва_України", "id": 226367}, {"name": "Видавництва_США", "id": 604491}, {"name": "Видавництва_СРСР", "id": 1530551}, {"name": "Кодування_символів", "id": 214039}, {"name": "Історія_книги", "id": 507199}, {"name": "Українські_історичні_періодичні_видання", "id": 316485}, {"name": "Газети_минулого", "id": 1536373}, {"name": "Журнали_Російської_імперії", "id": 1379216}, {"name": "Типографія", "id": 132958}, {"name": "Енциклопедії", "id": 21631}, {"name": "Книги", "id": 43544}, {"name": "Словники", "id": 71536}, {"name": "Географічні_карти", "id": 1064648}, {"name": "Онлайн-бібліотеки", "id": 13527}, {"name": "Наукові_журнали", "id": 365847}, {"name": "Медичні_журнали", "id": 605036}, {"name": "Щомісячні_журнали", "id": 568006}, {"name": "Щотижневі_журнали", "id": 604282}, {"name": "Щоквартальні_журнали", "id": 604577}, {"name": "Друковані_видання,_закриті_1939", "id": 2431065}, {"name": "Видавці_відеоігор", "id": 502392}, {"name": "Відкритий_доступ", "id": 1116742}, {"name": "Наукові_видання_України", "id": 1015425}, {"name": "Українські_періодичні_видання", "id": 29003}, {"name": "Українські_видавці", "id": 152802}, {"name": "Випускники_Української_академії_друкарства", "id": 282368}, {"name": "Науковці_Української_академії_друкарства", "id": 500514}, {"name": "Ігри_Deep_Silver", "id": 4568673}, {"name": "Журнали_видавництва_Elsevier", "id": 4782580}, {"name": "Ігри_Paradox_Interactive", "id": 503416}]}