{"name": "Митці_Києва", "id": 3213460, "predecessors": [{"name": "Культура_Києва", "id": 498515}, {"name": "Українські_митці", "id": 152939}, {"name": "Персоналії:Київ", "id": 79771}], "successors": [{"name": "Архітектори_Києва", "id": 558168}, {"name": "Письменники_Києва", "id": 1608050}, {"name": "Скульптори_Києва", "id": 1609174}, {"name": "Художники_Києва", "id": 2202214}, {"name": "Артисти_балету_Національної_опери_України", "id": 4493640}, {"name": "Актори_Київського_академічного_театру_драми_і_комедії_на_лівому_березі_Дніпра", "id": 614496}, {"name": "Актори_Національного_академічного_драматичного_театру_імені_Івана_Франка", "id": 616020}, {"name": "Актори_Київського_академічного_Молодого_театру", "id": 618643}, {"name": "Актори_Київського_національного_академічного_театру_оперети", "id": 1810787}, {"name": "Актори_Театру_Миколи_Садовського", "id": 1814510}, {"name": "Актори_Національного_академічного_драматичного_театру_імені_Лесі_Українки", "id": 4469388}, {"name": "Персоналії:Київський_національний_академічний_театр_оперети", "id": 1844080}, {"name": "Персоналії:Молодий_театр_Леся_Курбаса", "id": 1928581}, {"name": "Випускники_Музично-драматичної_школи_Миколи_Лисенка", "id": 1892758}, {"name": "Працівники_Кіностудії_ім._Довженка", "id": 2409729}, {"name": "Персоналії:Укртелефільм", "id": 2594305}, {"name": "Працівники_Київнаукфільму", "id": 3136615}, {"name": "Співаки_Національної_опери_України", "id": 4493604}, {"name": "Диригенти_Національної_опери_України", "id": 4493633}]}