{"name": "Лауреати_премії_«Оскар»", "id": 339270, "predecessors": [{"name": "Премія_«Оскар»", "id": 424393}, {"name": "ЗМІ", "id": 34446}], "successors": [{"name": "Лауреати_премії_«Оскар»_за_найкращу_режисерську_роботу", "id": 726862}, {"name": "Лауреати_премії_«Оскар»_за_найкращу_чоловічу_роль", "id": 1663720}, {"name": "Лауреати_премії_«Оскар»_за_найкращу_чоловічу_роль_другого_плану", "id": 1663722}, {"name": "Лауреати_премії_«Оскар»_за_найкращу_жіночу_роль", "id": 1665434}, {"name": "Лауреати_премії_«Оскар»_за_найкращу_жіночу_роль_другого_плану", "id": 1665438}, {"name": "Лауреати_премії_«Оскар»_за_найкращий_оригінальний_сценарій", "id": 1665461}, {"name": "Лауреати_премії_«Оскар»_за_найкращий_адаптований_сценарій", "id": 1665483}, {"name": "Лауреати_премії_«Оскар»_за_найкращу_операторську_роботу", "id": 1666018}, {"name": "Лауреати_премії_«Оскар»_за_найкращий_фільм_іноземною_мовою", "id": 2030655}, {"name": "Фільми_—_лауреати_премії_«Оскар»_за_найкращий_фільм", "id": 2261336}]}