{"name": "Збройні_сили_Росії", "id": 351167, "predecessors": [{"name": "Політика_Росії", "id": 51141}, {"name": "Військова_справа", "id": 16457}, {"name": "Фізична_географія", "id": 17516}, {"name": "Земля", "id": 49013}], "successors": [{"name": "Російська_гвардія", "id": 2241919}, {"name": "Російські_колабораціоністські_формування_в_Другій_світовій_війні", "id": 1139487}, {"name": "Зенітно-ракетні_комплекси_Росії", "id": 1805093}, {"name": "Військовики_десантних_військ_Росії", "id": 4484863}, {"name": "Авіабази_ВПС_Росії", "id": 648714}, {"name": "Ракетники_РВСП_СРСР_і_Росії", "id": 3405471}, {"name": "Мотострілецькі_бригади_Росії", "id": 2238869}, {"name": "Військовики_мотострілецьких_військ_Росії", "id": 4492687}]}