{"name": "Хокей_у_Швеції", "id": 624290, "predecessors": [{"name": "Розваги", "id": 188198}], "successors": [{"name": "Шведські_хокеїсти", "id": 151116}, {"name": "Хокейні_клуби_Швеції", "id": 934706}, {"name": "Хокеїсти_«Юргордена»", "id": 624840}, {"name": "Хокеїсти_«Фер'єстада»", "id": 732160}, {"name": "Хокеїсти_«Тімро»", "id": 815800}, {"name": "Хокеїсти_«Шеллефтео»", "id": 815866}, {"name": "Хокеїсти_«Лулео»", "id": 815868}, {"name": "Хокеїсти_«Регле»", "id": 816346}, {"name": "Хокеїсти_«Брюнеса»", "id": 863917}, {"name": "Хокеїсти_«Лінчепінга»", "id": 863918}, {"name": "Хокеїсти_МОДО", "id": 864114}, {"name": "Хокеїсти_«Фрелунди»", "id": 870390}, {"name": "Хокеїсти_«Мальме»", "id": 872485}, {"name": "Хокеїсти_АІКа", "id": 898774}, {"name": "Хокеїсти_«Седертельє»", "id": 898775}, {"name": "Хокеїсти_«Лександса»", "id": 902460}, {"name": "Хокеїсти_ГВ-71", "id": 978167}, {"name": "Шведські_хокейні_ігри", "id": 1815228}, {"name": "Чемпіонат_Швеції_із_хокею", "id": 2095278}]}