{"name": "Ссавці_Азії", "id": 814649, "predecessors": [{"name": "Земля", "id": 49013}], "successors": [{"name": "Ссавці_Японії", "id": 765531}, {"name": "Ссавці_Камбоджі", "id": 1456552}, {"name": "Ссавці_Китаю", "id": 1456553}, {"name": "Ссавці_Індії", "id": 1456556}, {"name": "Ссавці_Індонезії", "id": 1456557}, {"name": "Ссавці_Лаосу", "id": 1456559}, {"name": "Ссавці_Малайзії", "id": 1456562}, {"name": "Ссавці_М'янми", "id": 1456564}, {"name": "Ссавці_Непалу", "id": 1456568}, {"name": "Ссавці_Пакистану", "id": 1456569}, {"name": "Ссавці_Філіппін", "id": 1456572}, {"name": "Ссавці_Таїланду", "id": 1456577}, {"name": "Ссавці_В'єтнаму", "id": 1456578}, {"name": "Ссавці_Шрі-Ланки", "id": 1509153}, {"name": "Ссавці_Тайваню", "id": 1510526}, {"name": "Ссавці_Ірану", "id": 1510692}, {"name": "Ссавці_Казахстану", "id": 1510693}, {"name": "Ссавці_Азербайджану", "id": 1552938}, {"name": "Ссавці_Брунею", "id": 1587003}, {"name": "Ссавці_Туреччини", "id": 1845884}, {"name": "Ссавці_Монголії", "id": 2217946}, {"name": "Викопні_ссавці_Азії", "id": 5174924}]}